[{"elements": [{"type": "function", "name": "relay", "source_mapping": {"start": 1666, "length": 543, "filename_used": "/home/sencha/optimism-dai-bridge/contracts/l2/L2GovernanceRelay.sol", "filename_relative": "contracts/l2/L2GovernanceRelay.sol", "filename_absolute": "/home/sencha/optimism-dai-bridge/contracts/l2/L2GovernanceRelay.sol", "filename_short": "contracts/l2/L2GovernanceRelay.sol", "is_dependency": false, "lines": [54, 55, 56, 57, 58, 59, 60, 61, 62, 63, 64, 65, 66, 67, 68], "starting_column": 3, "ending_column": 4}, "type_specific_fields": {"parent": {"type": "contract", "name": "L2GovernanceRelay", "source_mapping": {"start": 958, "length": 1253, "filename_used": "/home/sencha/optimism-dai-bridge/contracts/l2/L2GovernanceRelay.sol", "filename_relative": "contracts/l2/L2GovernanceRelay.sol", "filename_absolute": "/home/sencha/optimism-dai-bridge/contracts/l2/L2GovernanceRelay.sol", "filename_short": "contracts/l2/L2GovernanceRelay.sol", "is_dependency": false, "lines": [22, 23, 24, 25, 26, 27, 28, 29, 30, 31, 32, 33, 34, 35, 36, 37, 38, 39, 40, 41, 42, 43, 44, 45, 46, 47, 48, 49, 50, 51, 52, 53, 54, 55, 56, 57, 58, 59, 60, 61, 62, 63, 64, 65, 66, 67, 68, 69], "starting_column": 1, "ending_column": 2}}, "signature": "relay(address,bytes)"}}, {"type": "node", "name": "(ok,None) = target.delegatecall(targetData)", "source_mapping": {"start": 1982, "length": 39, "filename_used": "/home/sencha/optimism-dai-bridge/contracts/l2/L2GovernanceRelay.sol", "filename_relative": "contracts/l2/L2GovernanceRelay.sol", "filename_absolute": "/home/sencha/optimism-dai-bridge/contracts/l2/L2GovernanceRelay.sol", "filename_short": "contracts/l2/L2GovernanceRelay.sol", "is_dependency": false, "lines": [64], "starting_column": 5, "ending_column": 44}, "type_specific_fields": {"parent": {"type": "function", "name": "relay", "source_mapping": {"start": 1666, "length": 543, "filename_used": "/home/sencha/optimism-dai-bridge/contracts/l2/L2GovernanceRelay.sol", "filename_relative": "contracts/l2/L2GovernanceRelay.sol", "filename_absolute": "/home/sencha/optimism-dai-bridge/contracts/l2/L2GovernanceRelay.sol", "filename_short": "contracts/l2/L2GovernanceRelay.sol", "is_dependency": false, "lines": [54, 55, 56, 57, 58, 59, 60, 61, 62, 63, 64, 65, 66, 67, 68], "starting_column": 3, "ending_column": 4}, "type_specific_fields": {"parent": {"type": "contract", "name": "L2GovernanceRelay", "source_mapping": {"start": 958, "length": 1253, "filename_used": "/home/sencha/optimism-dai-bridge/contracts/l2/L2GovernanceRelay.sol", "filename_relative": "contracts/l2/L2GovernanceRelay.sol", "filename_absolute": "/home/sencha/optimism-dai-bridge/contracts/l2/L2GovernanceRelay.sol", "filename_short": "contracts/l2/L2GovernanceRelay.sol", "is_dependency": false, "lines": [22, 23, 24, 25, 26, 27, 28, 29, 30, 31, 32, 33, 34, 35, 36, 37, 38, 39, 40, 41, 42, 43, 44, 45, 46, 47, 48, 49, 50, 51, 52, 53, 54, 55, 56, 57, 58, 59, 60, 61, 62, 63, 64, 65, 66, 67, 68, 69], "starting_column": 1, "ending_column": 2}}, "signature": "relay(address,bytes)"}}}}], "description": "L2GovernanceRelay.relay(address,bytes) (contracts/l2/L2GovernanceRelay.sol#54-68) uses delegatecall to a input-controlled function id\n\t- (ok,None) = target.delegatecall(targetData) (contracts/l2/L2GovernanceRelay.sol#64)\n", "markdown": "[L2GovernanceRelay.relay(address,bytes)](contracts/l2/L2GovernanceRelay.sol#L54-L68) uses delegatecall to a input-controlled function id\n\t- [(ok,None) = target.delegatecall(targetData)](contracts/l2/L2GovernanceRelay.sol#L64)\n", "first_markdown_element": "contracts/l2/L2GovernanceRelay.sol#L54-L68", "id": "99ea0b921b1cddacaf81fb045bbbd009e2fdf9267ce4f5b2f55739a375835722", "check": "controlled-delegatecall", "impact": "High", "confidence": "Medium"}, {"elements": [{"type": "function", "name": "_handleInitiateDeposit", "source_mapping": {"start": 2142, "length": 213, "filename_used": "/home/sencha/optimism-dai-bridge/contracts/l1/L1Gateway.sol", "filename_relative": "contracts/l1/L1Gateway.sol", "filename_absolute": "/home/sencha/optimism-dai-bridge/contracts/l1/L1Gateway.sol", "filename_short": "contracts/l1/L1Gateway.sol", "is_dependency": false, "lines": [72, 73, 74, 75, 76, 77, 78, 79, 80], "starting_column": 3, "ending_column": 4}, "type_specific_fields": {"parent": {"type": "contract", "name": "L1Gateway", "source_mapping": {"start": 1191, "length": 1356, "filename_used": "/home/sencha/optimism-dai-bridge/contracts/l1/L1Gateway.sol", "filename_relative": "contracts/l1/L1Gateway.sol", "filename_absolute": "/home/sencha/optimism-dai-bridge/contracts/l1/L1Gateway.sol", "filename_short": "contracts/l1/L1Gateway.sol", "is_dependency": false, "lines": [28, 29, 30, 31, 32, 33, 34, 35, 36, 37, 38, 39, 40, 41, 42, 43, 44, 45, 46, 47, 48, 49, 50, 51, 52, 53, 54, 55, 56, 57, 58, 59, 60, 61, 62, 63, 64, 65, 66, 67, 68, 69, 70, 71, 72, 73, 74, 75, 76, 77, 78, 79, 80, 81, 82, 83, 84, 85, 86], "starting_column": 1, "ending_column": 2}}, "signature": "_handleInitiateDeposit(address,address,uint256)"}}, {"type": "node", "name": "l1ERC20.transferFrom(_from,escrow,_amount)", "source_mapping": {"start": 2306, "length": 44, "filename_used": "/home/sencha/optimism-dai-bridge/contracts/l1/L1Gateway.sol", "filename_relative": "contracts/l1/L1Gateway.sol", "filename_absolute": "/home/sencha/optimism-dai-bridge/contracts/l1/L1Gateway.sol", "filename_short": "contracts/l1/L1Gateway.sol", "is_dependency": false, "lines": [79], "starting_column": 5, "ending_column": 49}, "type_specific_fields": {"parent": {"type": "function", "name": "_handleInitiateDeposit", "source_mapping": {"start": 2142, "length": 213, "filename_used": "/home/sencha/optimism-dai-bridge/contracts/l1/L1Gateway.sol", "filename_relative": "contracts/l1/L1Gateway.sol", "filename_absolute": "/home/sencha/optimism-dai-bridge/contracts/l1/L1Gateway.sol", "filename_short": "contracts/l1/L1Gateway.sol", "is_dependency": false, "lines": [72, 73, 74, 75, 76, 77, 78, 79, 80], "starting_column": 3, "ending_column": 4}, "type_specific_fields": {"parent": {"type": "contract", "name": "L1Gateway", "source_mapping": {"start": 1191, "length": 1356, "filename_used": "/home/sencha/optimism-dai-bridge/contracts/l1/L1Gateway.sol", "filename_relative": "contracts/l1/L1Gateway.sol", "filename_absolute": "/home/sencha/optimism-dai-bridge/contracts/l1/L1Gateway.sol", "filename_short": "contracts/l1/L1Gateway.sol", "is_dependency": false, "lines": [28, 29, 30, 31, 32, 33, 34, 35, 36, 37, 38, 39, 40, 41, 42, 43, 44, 45, 46, 47, 48, 49, 50, 51, 52, 53, 54, 55, 56, 57, 58, 59, 60, 61, 62, 63, 64, 65, 66, 67, 68, 69, 70, 71, 72, 73, 74, 75, 76, 77, 78, 79, 80, 81, 82, 83, 84, 85, 86], "starting_column": 1, "ending_column": 2}}, "signature": "_handleInitiateDeposit(address,address,uint256)"}}}}], "description": "L1Gateway._handleInitiateDeposit(address,address,uint256) (contracts/l1/L1Gateway.sol#72-80) ignores return value by l1ERC20.transferFrom(_from,escrow,_amount) (contracts/l1/L1Gateway.sol#79)\n", "markdown": "[L1Gateway._handleInitiateDeposit(address,address,uint256)](contracts/l1/L1Gateway.sol#L72-L80) ignores return value by [l1ERC20.transferFrom(_from,escrow,_amount)](contracts/l1/L1Gateway.sol#L79)\n", "first_markdown_element": "contracts/l1/L1Gateway.sol#L72-L80", "id": "13717d678e8784a39def22e5392b2553dc5e7729675b23d1688ebb49134d93cc", "check": "unchecked-transfer", "impact": "High", "confidence": "Medium"}, {"elements": [{"type": "function", "name": "_handleFinalizeWithdrawal", "source_mapping": {"start": 2359, "length": 186, "filename_used": "/home/sencha/optimism-dai-bridge/contracts/l1/L1Gateway.sol", "filename_relative": "contracts/l1/L1Gateway.sol", "filename_absolute": "/home/sencha/optimism-dai-bridge/contracts/l1/L1Gateway.sol", "filename_short": "contracts/l1/L1Gateway.sol", "is_dependency": false, "lines": [82, 83, 84, 85], "starting_column": 3, "ending_column": 4}, "type_specific_fields": {"parent": {"type": "contract", "name": "L1Gateway", "source_mapping": {"start": 1191, "length": 1356, "filename_used": "/home/sencha/optimism-dai-bridge/contracts/l1/L1Gateway.sol", "filename_relative": "contracts/l1/L1Gateway.sol", "filename_absolute": "/home/sencha/optimism-dai-bridge/contracts/l1/L1Gateway.sol", "filename_short": "contracts/l1/L1Gateway.sol", "is_dependency": false, "lines": [28, 29, 30, 31, 32, 33, 34, 35, 36, 37, 38, 39, 40, 41, 42, 43, 44, 45, 46, 47, 48, 49, 50, 51, 52, 53, 54, 55, 56, 57, 58, 59, 60, 61, 62, 63, 64, 65, 66, 67, 68, 69, 70, 71, 72, 73, 74, 75, 76, 77, 78, 79, 80, 81, 82, 83, 84, 85, 86], "starting_column": 1, "ending_column": 2}}, "signature": "_handleFinalizeWithdrawal(address,uint256)"}}, {"type": "node", "name": "l1ERC20.transferFrom(escrow,_to,_amount)", "source_mapping": {"start": 2498, "length": 42, "filename_used": "/home/sencha/optimism-dai-bridge/contracts/l1/L1Gateway.sol", "filename_relative": "contracts/l1/L1Gateway.sol", "filename_absolute": "/home/sencha/optimism-dai-bridge/contracts/l1/L1Gateway.sol", "filename_short": "contracts/l1/L1Gateway.sol", "is_dependency": false, "lines": [84], "starting_column": 5, "ending_column": 47}, "type_specific_fields": {"parent": {"type": "function", "name": "_handleFinalizeWithdrawal", "source_mapping": {"start": 2359, "length": 186, "filename_used": "/home/sencha/optimism-dai-bridge/contracts/l1/L1Gateway.sol", "filename_relative": "contracts/l1/L1Gateway.sol", "filename_absolute": "/home/sencha/optimism-dai-bridge/contracts/l1/L1Gateway.sol", "filename_short": "contracts/l1/L1Gateway.sol", "is_dependency": false, "lines": [82, 83, 84, 85], "starting_column": 3, "ending_column": 4}, "type_specific_fields": {"parent": {"type": "contract", "name": "L1Gateway", "source_mapping": {"start": 1191, "length": 1356, "filename_used": "/home/sencha/optimism-dai-bridge/contracts/l1/L1Gateway.sol", "filename_relative": "contracts/l1/L1Gateway.sol", "filename_absolute": "/home/sencha/optimism-dai-bridge/contracts/l1/L1Gateway.sol", "filename_short": "contracts/l1/L1Gateway.sol", "is_dependency": false, "lines": [28, 29, 30, 31, 32, 33, 34, 35, 36, 37, 38, 39, 40, 41, 42, 43, 44, 45, 46, 47, 48, 49, 50, 51, 52, 53, 54, 55, 56, 57, 58, 59, 60, 61, 62, 63, 64, 65, 66, 67, 68, 69, 70, 71, 72, 73, 74, 75, 76, 77, 78, 79, 80, 81, 82, 83, 84, 85, 86], "starting_column": 1, "ending_column": 2}}, "signature": "_handleFinalizeWithdrawal(address,uint256)"}}}}], "description": "L1Gateway._handleFinalizeWithdrawal(address,uint256) (contracts/l1/L1Gateway.sol#82-85) ignores return value by l1ERC20.transferFrom(escrow,_to,_amount) (contracts/l1/L1Gateway.sol#84)\n", "markdown": "[L1Gateway._handleFinalizeWithdrawal(address,uint256)](contracts/l1/L1Gateway.sol#L82-L85) ignores return value by [l1ERC20.transferFrom(escrow,_to,_amount)](contracts/l1/L1Gateway.sol#L84)\n", "first_markdown_element": "contracts/l1/L1Gateway.sol#L82-L85", "id": "ab22e4b9f231e49fb890a66ea9240248ae4614fe2a71fc6f4a8d7f0a6b9febf5", "check": "unchecked-transfer", "impact": "High", "confidence": "Medium"}, {"elements": [{"type": "function", "name": "transfer", "source_mapping": {"start": 1987, "length": 392, "filename_used": "/home/sencha/optimism-dai-bridge/contracts/test/DaiEchidnaTest.sol", "filename_relative": "contracts/test/DaiEchidnaTest.sol", "filename_absolute": "/home/sencha/optimism-dai-bridge/contracts/test/DaiEchidnaTest.sol", "filename_short": "contracts/test/DaiEchidnaTest.sol", "is_dependency": false, "lines": [59, 60, 61, 62, 63, 64, 65, 66], "starting_column": 5, "ending_column": 6}, "type_specific_fields": {"parent": {"type": "contract", "name": "DaiEchidnaTest", "source_mapping": {"start": 335, "length": 2534, "filename_used": "/home/sencha/optimism-dai-bridge/contracts/test/DaiEchidnaTest.sol", "filename_relative": "contracts/test/DaiEchidnaTest.sol", "filename_absolute": "/home/sencha/optimism-dai-bridge/contracts/test/DaiEchidnaTest.sol", "filename_short": "contracts/test/DaiEchidnaTest.sol", "is_dependency": false, "lines": [14, 15, 16, 17, 18, 19, 20, 21, 22, 23, 24, 25, 26, 27, 28, 29, 30, 31, 32, 33, 34, 35, 36, 37, 38, 39, 40, 41, 42, 43, 44, 45, 46, 47, 48, 49, 50, 51, 52, 53, 54, 55, 56, 57, 58, 59, 60, 61, 62, 63, 64, 65, 66, 67, 68, 69, 70, 71, 72, 73, 74, 75, 76, 77], "starting_column": 1, "ending_column": 2}}, "signature": "transfer(uint256)"}}, {"type": "node", "name": "dai.transfer(holder,wad)", "source_mapping": {"start": 2210, "length": 25, "filename_used": "/home/sencha/optimism-dai-bridge/contracts/test/DaiEchidnaTest.sol", "filename_relative": "contracts/test/DaiEchidnaTest.sol", "filename_absolute": "/home/sencha/optimism-dai-bridge/contracts/test/DaiEchidnaTest.sol", "filename_short": "contracts/test/DaiEchidnaTest.sol", "is_dependency": false, "lines": [63], "starting_column": 9, "ending_column": 34}, "type_specific_fields": {"parent": {"type": "function", "name": "transfer", "source_mapping": {"start": 1987, "length": 392, "filename_used": "/home/sencha/optimism-dai-bridge/contracts/test/DaiEchidnaTest.sol", "filename_relative": "contracts/test/DaiEchidnaTest.sol", "filename_absolute": "/home/sencha/optimism-dai-bridge/contracts/test/DaiEchidnaTest.sol", "filename_short": "contracts/test/DaiEchidnaTest.sol", "is_dependency": false, "lines": [59, 60, 61, 62, 63, 64, 65, 66], "starting_column": 5, "ending_column": 6}, "type_specific_fields": {"parent": {"type": "contract", "name": "DaiEchidnaTest", "source_mapping": {"start": 335, "length": 2534, "filename_used": "/home/sencha/optimism-dai-bridge/contracts/test/DaiEchidnaTest.sol", "filename_relative": "contracts/test/DaiEchidnaTest.sol", "filename_absolute": "/home/sencha/optimism-dai-bridge/contracts/test/DaiEchidnaTest.sol", "filename_short": "contracts/test/DaiEchidnaTest.sol", "is_dependency": false, "lines": [14, 15, 16, 17, 18, 19, 20, 21, 22, 23, 24, 25, 26, 27, 28, 29, 30, 31, 32, 33, 34, 35, 36, 37, 38, 39, 40, 41, 42, 43, 44, 45, 46, 47, 48, 49, 50, 51, 52, 53, 54, 55, 56, 57, 58, 59, 60, 61, 62, 63, 64, 65, 66, 67, 68, 69, 70, 71, 72, 73, 74, 75, 76, 77], "starting_column": 1, "ending_column": 2}}, "signature": "transfer(uint256)"}}}}], "description": "DaiEchidnaTest.transfer(uint256) (contracts/test/DaiEchidnaTest.sol#59-66) ignores return value by dai.transfer(holder,wad) (contracts/test/DaiEchidnaTest.sol#63)\n", "markdown": "[DaiEchidnaTest.transfer(uint256)](contracts/test/DaiEchidnaTest.sol#L59-L66) ignores return value by [dai.transfer(holder,wad)](contracts/test/DaiEchidnaTest.sol#L63)\n", "first_markdown_element": "contracts/test/DaiEchidnaTest.sol#L59-L66", "id": "1efae11074aeefc4468f0442dbf56a7703896500e5bf839af377066030d43682", "check": "unchecked-transfer", "impact": "High", "confidence": "Medium"}, {"elements": [{"type": "function", "name": "transferFrom", "source_mapping": {"start": 2448, "length": 419, "filename_used": "/home/sencha/optimism-dai-bridge/contracts/test/DaiEchidnaTest.sol", "filename_relative": "contracts/test/DaiEchidnaTest.sol", "filename_absolute": "/home/sencha/optimism-dai-bridge/contracts/test/DaiEchidnaTest.sol", "filename_short": "contracts/test/DaiEchidnaTest.sol", "is_dependency": false, "lines": [69, 70, 71, 72, 73, 74, 75, 76], "starting_column": 5, "ending_column": 6}, "type_specific_fields": {"parent": {"type": "contract", "name": "DaiEchidnaTest", "source_mapping": {"start": 335, "length": 2534, "filename_used": "/home/sencha/optimism-dai-bridge/contracts/test/DaiEchidnaTest.sol", "filename_relative": "contracts/test/DaiEchidnaTest.sol", "filename_absolute": "/home/sencha/optimism-dai-bridge/contracts/test/DaiEchidnaTest.sol", "filename_short": "contracts/test/DaiEchidnaTest.sol", "is_dependency": false, "lines": [14, 15, 16, 17, 18, 19, 20, 21, 22, 23, 24, 25, 26, 27, 28, 29, 30, 31, 32, 33, 34, 35, 36, 37, 38, 39, 40, 41, 42, 43, 44, 45, 46, 47, 48, 49, 50, 51, 52, 53, 54, 55, 56, 57, 58, 59, 60, 61, 62, 63, 64, 65, 66, 67, 68, 69, 70, 71, 72, 73, 74, 75, 76, 77], "starting_column": 1, "ending_column": 2}}, "signature": "transferFrom(uint256)"}}, {"type": "node", "name": "dai.transferFrom(holder,address(this),wad)", "source_mapping": {"start": 2679, "length": 44, "filename_used": "/home/sencha/optimism-dai-bridge/contracts/test/DaiEchidnaTest.sol", "filename_relative": "contracts/test/DaiEchidnaTest.sol", "filename_absolute": "/home/sencha/optimism-dai-bridge/contracts/test/DaiEchidnaTest.sol", "filename_short": "contracts/test/DaiEchidnaTest.sol", "is_dependency": false, "lines": [73], "starting_column": 9, "ending_column": 53}, "type_specific_fields": {"parent": {"type": "function", "name": "transferFrom", "source_mapping": {"start": 2448, "length": 419, "filename_used": "/home/sencha/optimism-dai-bridge/contracts/test/DaiEchidnaTest.sol", "filename_relative": "contracts/test/DaiEchidnaTest.sol", "filename_absolute": "/home/sencha/optimism-dai-bridge/contracts/test/DaiEchidnaTest.sol", "filename_short": "contracts/test/DaiEchidnaTest.sol", "is_dependency": false, "lines": [69, 70, 71, 72, 73, 74, 75, 76], "starting_column": 5, "ending_column": 6}, "type_specific_fields": {"parent": {"type": "contract", "name": "DaiEchidnaTest", "source_mapping": {"start": 335, "length": 2534, "filename_used": "/home/sencha/optimism-dai-bridge/contracts/test/DaiEchidnaTest.sol", "filename_relative": "contracts/test/DaiEchidnaTest.sol", "filename_absolute": "/home/sencha/optimism-dai-bridge/contracts/test/DaiEchidnaTest.sol", "filename_short": "contracts/test/DaiEchidnaTest.sol", "is_dependency": false, "lines": [14, 15, 16, 17, 18, 19, 20, 21, 22, 23, 24, 25, 26, 27, 28, 29, 30, 31, 32, 33, 34, 35, 36, 37, 38, 39, 40, 41, 42, 43, 44, 45, 46, 47, 48, 49, 50, 51, 52, 53, 54, 55, 56, 57, 58, 59, 60, 61, 62, 63, 64, 65, 66, 67, 68, 69, 70, 71, 72, 73, 74, 75, 76, 77], "starting_column": 1, "ending_column": 2}}, "signature": "transferFrom(uint256)"}}}}], "description": "DaiEchidnaTest.transferFrom(uint256) (contracts/test/DaiEchidnaTest.sol#69-76) ignores return value by dai.transferFrom(holder,address(this),wad) (contracts/test/DaiEchidnaTest.sol#73)\n", "markdown": "[DaiEchidnaTest.transferFrom(uint256)](contracts/test/DaiEchidnaTest.sol#L69-L76) ignores return value by [dai.transferFrom(holder,address(this),wad)](contracts/test/DaiEchidnaTest.sol#L73)\n", "first_markdown_element": "contracts/test/DaiEchidnaTest.sol#L69-L76", "id": "67a1b11627ef957bf24ff3bb744be122deb46a3a0e7bb54dcf7737156f227180", "check": "unchecked-transfer", "impact": "High", "confidence": "Medium"}, {"elements": [{"type": "contract", "name": "ApproveLike", "source_mapping": {"start": 799, "length": 72, "filename_used": "/home/sencha/optimism-dai-bridge/contracts/l1/L1Escrow.sol", "filename_relative": "contracts/l1/L1Escrow.sol", "filename_absolute": "/home/sencha/optimism-dai-bridge/contracts/l1/L1Escrow.sol", "filename_short": "contracts/l1/L1Escrow.sol", "is_dependency": false, "lines": [19, 20, 21], "starting_column": 1, "ending_column": 2}}, {"type": "function", "name": "approve", "source_mapping": {"start": 825, "length": 44, "filename_used": "/home/sencha/optimism-dai-bridge/contracts/l1/L1Escrow.sol", "filename_relative": "contracts/l1/L1Escrow.sol", "filename_absolute": "/home/sencha/optimism-dai-bridge/contracts/l1/L1Escrow.sol", "filename_short": "contracts/l1/L1Escrow.sol", "is_dependency": false, "lines": [20], "starting_column": 3, "ending_column": 47}, "type_specific_fields": {"parent": {"type": "contract", "name": "ApproveLike", "source_mapping": {"start": 799, "length": 72, "filename_used": "/home/sencha/optimism-dai-bridge/contracts/l1/L1Escrow.sol", "filename_relative": "contracts/l1/L1Escrow.sol", "filename_absolute": "/home/sencha/optimism-dai-bridge/contracts/l1/L1Escrow.sol", "filename_short": "contracts/l1/L1Escrow.sol", "is_dependency": false, "lines": [19, 20, 21], "starting_column": 1, "ending_column": 2}}, "signature": "approve(address,uint256)"}}], "description": "ApproveLike (contracts/l1/L1Escrow.sol#19-21) has incorrect ERC20 function interface:ApproveLike.approve(address,uint256) (contracts/l1/L1Escrow.sol#20)\n", "markdown": "[ApproveLike](contracts/l1/L1Escrow.sol#L19-L21) has incorrect ERC20 function interface:[ApproveLike.approve(address,uint256)](contracts/l1/L1Escrow.sol#L20)\n", "first_markdown_element": "contracts/l1/L1Escrow.sol#L19-L21", "id": "fc91b4cd59603501d2861b1b88b521a41006dcac3df5a739fca69516f7459fcf", "check": "erc20-interface", "impact": "Medium", "confidence": "High"}, {"elements": [{"type": "function", "name": "burn", "source_mapping": {"start": 1566, "length": 356, "filename_used": "/home/sencha/optimism-dai-bridge/contracts/test/DaiEchidnaTest.sol", "filename_relative": "contracts/test/DaiEchidnaTest.sol", "filename_absolute": "/home/sencha/optimism-dai-bridge/contracts/test/DaiEchidnaTest.sol", "filename_short": "contracts/test/DaiEchidnaTest.sol", "is_dependency": false, "lines": [49, 50, 51, 52, 53, 54, 55, 56], "starting_column": 5, "ending_column": 6}, "type_specific_fields": {"parent": {"type": "contract", "name": "DaiEchidnaTest", "source_mapping": {"start": 335, "length": 2534, "filename_used": "/home/sencha/optimism-dai-bridge/contracts/test/DaiEchidnaTest.sol", "filename_relative": "contracts/test/DaiEchidnaTest.sol", "filename_absolute": "/home/sencha/optimism-dai-bridge/contracts/test/DaiEchidnaTest.sol", "filename_short": "contracts/test/DaiEchidnaTest.sol", "is_dependency": false, "lines": [14, 15, 16, 17, 18, 19, 20, 21, 22, 23, 24, 25, 26, 27, 28, 29, 30, 31, 32, 33, 34, 35, 36, 37, 38, 39, 40, 41, 42, 43, 44, 45, 46, 47, 48, 49, 50, 51, 52, 53, 54, 55, 56, 57, 58, 59, 60, 61, 62, 63, 64, 65, 66, 67, 68, 69, 70, 71, 72, 73, 74, 75, 76, 77], "starting_column": 1, "ending_column": 2}}, "signature": "burn(uint256)"}}, {"type": "node", "name": "assert(bool)(dai.balanceOf(holder) == sub(holderBalance,wad))", "source_mapping": {"start": 1804, "length": 56, "filename_used": "/home/sencha/optimism-dai-bridge/contracts/test/DaiEchidnaTest.sol", "filename_relative": "contracts/test/DaiEchidnaTest.sol", "filename_absolute": "/home/sencha/optimism-dai-bridge/contracts/test/DaiEchidnaTest.sol", "filename_short": "contracts/test/DaiEchidnaTest.sol", "is_dependency": false, "lines": [54], "starting_column": 9, "ending_column": 65}, "type_specific_fields": {"parent": {"type": "function", "name": "burn", "source_mapping": {"start": 1566, "length": 356, "filename_used": "/home/sencha/optimism-dai-bridge/contracts/test/DaiEchidnaTest.sol", "filename_relative": "contracts/test/DaiEchidnaTest.sol", "filename_absolute": "/home/sencha/optimism-dai-bridge/contracts/test/DaiEchidnaTest.sol", "filename_short": "contracts/test/DaiEchidnaTest.sol", "is_dependency": false, "lines": [49, 50, 51, 52, 53, 54, 55, 56], "starting_column": 5, "ending_column": 6}, "type_specific_fields": {"parent": {"type": "contract", "name": "DaiEchidnaTest", "source_mapping": {"start": 335, "length": 2534, "filename_used": "/home/sencha/optimism-dai-bridge/contracts/test/DaiEchidnaTest.sol", "filename_relative": "contracts/test/DaiEchidnaTest.sol", "filename_absolute": "/home/sencha/optimism-dai-bridge/contracts/test/DaiEchidnaTest.sol", "filename_short": "contracts/test/DaiEchidnaTest.sol", "is_dependency": false, "lines": [14, 15, 16, 17, 18, 19, 20, 21, 22, 23, 24, 25, 26, 27, 28, 29, 30, 31, 32, 33, 34, 35, 36, 37, 38, 39, 40, 41, 42, 43, 44, 45, 46, 47, 48, 49, 50, 51, 52, 53, 54, 55, 56, 57, 58, 59, 60, 61, 62, 63, 64, 65, 66, 67, 68, 69, 70, 71, 72, 73, 74, 75, 76, 77], "starting_column": 1, "ending_column": 2}}, "signature": "burn(uint256)"}}}}], "description": "DaiEchidnaTest.burn(uint256) (contracts/test/DaiEchidnaTest.sol#49-56) uses a dangerous strict equality:\n\t- assert(bool)(dai.balanceOf(holder) == sub(holderBalance,wad)) (contracts/test/DaiEchidnaTest.sol#54)\n", "markdown": "[DaiEchidnaTest.burn(uint256)](contracts/test/DaiEchidnaTest.sol#L49-L56) uses a dangerous strict equality:\n\t- [assert(bool)(dai.balanceOf(holder) == sub(holderBalance,wad))](contracts/test/DaiEchidnaTest.sol#L54)\n", "first_markdown_element": "contracts/test/DaiEchidnaTest.sol#L49-L56", "id": "5ff2088a726f8fa9278fd4df0a39b1a68f6775d3192e7b730fcc3c6e3a2ea938", "check": "incorrect-equality", "impact": "Medium", "confidence": "High"}, {"elements": [{"type": "function", "name": "burn", "source_mapping": {"start": 1566, "length": 356, "filename_used": "/home/sencha/optimism-dai-bridge/contracts/test/DaiEchidnaTest.sol", "filename_relative": "contracts/test/DaiEchidnaTest.sol", "filename_absolute": "/home/sencha/optimism-dai-bridge/contracts/test/DaiEchidnaTest.sol", "filename_short": "contracts/test/DaiEchidnaTest.sol", "is_dependency": false, "lines": [49, 50, 51, 52, 53, 54, 55, 56], "starting_column": 5, "ending_column": 6}, "type_specific_fields": {"parent": {"type": "contract", "name": "DaiEchidnaTest", "source_mapping": {"start": 335, "length": 2534, "filename_used": "/home/sencha/optimism-dai-bridge/contracts/test/DaiEchidnaTest.sol", "filename_relative": "contracts/test/DaiEchidnaTest.sol", "filename_absolute": "/home/sencha/optimism-dai-bridge/contracts/test/DaiEchidnaTest.sol", "filename_short": "contracts/test/DaiEchidnaTest.sol", "is_dependency": false, "lines": [14, 15, 16, 17, 18, 19, 20, 21, 22, 23, 24, 25, 26, 27, 28, 29, 30, 31, 32, 33, 34, 35, 36, 37, 38, 39, 40, 41, 42, 43, 44, 45, 46, 47, 48, 49, 50, 51, 52, 53, 54, 55, 56, 57, 58, 59, 60, 61, 62, 63, 64, 65, 66, 67, 68, 69, 70, 71, 72, 73, 74, 75, 76, 77], "starting_column": 1, "ending_column": 2}}, "signature": "burn(uint256)"}}, {"type": "node", "name": "holderBalance == 0", "source_mapping": {"start": 1709, "length": 54, "filename_used": "/home/sencha/optimism-dai-bridge/contracts/test/DaiEchidnaTest.sol", "filename_relative": "contracts/test/DaiEchidnaTest.sol", "filename_absolute": "/home/sencha/optimism-dai-bridge/contracts/test/DaiEchidnaTest.sol", "filename_short": "contracts/test/DaiEchidnaTest.sol", "is_dependency": false, "lines": [52], "starting_column": 9, "ending_column": 63}, "type_specific_fields": {"parent": {"type": "function", "name": "burn", "source_mapping": {"start": 1566, "length": 356, "filename_used": "/home/sencha/optimism-dai-bridge/contracts/test/DaiEchidnaTest.sol", "filename_relative": "contracts/test/DaiEchidnaTest.sol", "filename_absolute": "/home/sencha/optimism-dai-bridge/contracts/test/DaiEchidnaTest.sol", "filename_short": "contracts/test/DaiEchidnaTest.sol", "is_dependency": false, "lines": [49, 50, 51, 52, 53, 54, 55, 56], "starting_column": 5, "ending_column": 6}, "type_specific_fields": {"parent": {"type": "contract", "name": "DaiEchidnaTest", "source_mapping": {"start": 335, "length": 2534, "filename_used": "/home/sencha/optimism-dai-bridge/contracts/test/DaiEchidnaTest.sol", "filename_relative": "contracts/test/DaiEchidnaTest.sol", "filename_absolute": "/home/sencha/optimism-dai-bridge/contracts/test/DaiEchidnaTest.sol", "filename_short": "contracts/test/DaiEchidnaTest.sol", "is_dependency": false, "lines": [14, 15, 16, 17, 18, 19, 20, 21, 22, 23, 24, 25, 26, 27, 28, 29, 30, 31, 32, 33, 34, 35, 36, 37, 38, 39, 40, 41, 42, 43, 44, 45, 46, 47, 48, 49, 50, 51, 52, 53, 54, 55, 56, 57, 58, 59, 60, 61, 62, 63, 64, 65, 66, 67, 68, 69, 70, 71, 72, 73, 74, 75, 76, 77], "starting_column": 1, "ending_column": 2}}, "signature": "burn(uint256)"}}}}], "description": "DaiEchidnaTest.burn(uint256) (contracts/test/DaiEchidnaTest.sol#49-56) uses a dangerous strict equality:\n\t- holderBalance == 0 (contracts/test/DaiEchidnaTest.sol#52)\n", "markdown": "[DaiEchidnaTest.burn(uint256)](contracts/test/DaiEchidnaTest.sol#L49-L56) uses a dangerous strict equality:\n\t- [holderBalance == 0](contracts/test/DaiEchidnaTest.sol#L52)\n", "first_markdown_element": "contracts/test/DaiEchidnaTest.sol#L49-L56", "id": "541146263fcf514c4004728f297c8511857393b8aada558f1f0f2058937a6671", "check": "incorrect-equality", "impact": "Medium", "confidence": "High"}, {"elements": [{"type": "function", "name": "mint", "source_mapping": {"start": 1164, "length": 341, "filename_used": "/home/sencha/optimism-dai-bridge/contracts/test/DaiEchidnaTest.sol", "filename_relative": "contracts/test/DaiEchidnaTest.sol", "filename_absolute": "/home/sencha/optimism-dai-bridge/contracts/test/DaiEchidnaTest.sol", "filename_short": "contracts/test/DaiEchidnaTest.sol", "is_dependency": false, "lines": [39, 40, 41, 42, 43, 44, 45, 46], "starting_column": 5, "ending_column": 6}, "type_specific_fields": {"parent": {"type": "contract", "name": "DaiEchidnaTest", "source_mapping": {"start": 335, "length": 2534, "filename_used": "/home/sencha/optimism-dai-bridge/contracts/test/DaiEchidnaTest.sol", "filename_relative": "contracts/test/DaiEchidnaTest.sol", "filename_absolute": "/home/sencha/optimism-dai-bridge/contracts/test/DaiEchidnaTest.sol", "filename_short": "contracts/test/DaiEchidnaTest.sol", "is_dependency": false, "lines": [14, 15, 16, 17, 18, 19, 20, 21, 22, 23, 24, 25, 26, 27, 28, 29, 30, 31, 32, 33, 34, 35, 36, 37, 38, 39, 40, 41, 42, 43, 44, 45, 46, 47, 48, 49, 50, 51, 52, 53, 54, 55, 56, 57, 58, 59, 60, 61, 62, 63, 64, 65, 66, 67, 68, 69, 70, 71, 72, 73, 74, 75, 76, 77], "starting_column": 1, "ending_column": 2}}, "signature": "mint(uint256)"}}, {"type": "node", "name": "assert(bool)(dai.balanceOf(holder) == add(holderBalance,wad))", "source_mapping": {"start": 1387, "length": 56, "filename_used": "/home/sencha/optimism-dai-bridge/contracts/test/DaiEchidnaTest.sol", "filename_relative": "contracts/test/DaiEchidnaTest.sol", "filename_absolute": "/home/sencha/optimism-dai-bridge/contracts/test/DaiEchidnaTest.sol", "filename_short": "contracts/test/DaiEchidnaTest.sol", "is_dependency": false, "lines": [44], "starting_column": 9, "ending_column": 65}, "type_specific_fields": {"parent": {"type": "function", "name": "mint", "source_mapping": {"start": 1164, "length": 341, "filename_used": "/home/sencha/optimism-dai-bridge/contracts/test/DaiEchidnaTest.sol", "filename_relative": "contracts/test/DaiEchidnaTest.sol", "filename_absolute": "/home/sencha/optimism-dai-bridge/contracts/test/DaiEchidnaTest.sol", "filename_short": "contracts/test/DaiEchidnaTest.sol", "is_dependency": false, "lines": [39, 40, 41, 42, 43, 44, 45, 46], "starting_column": 5, "ending_column": 6}, "type_specific_fields": {"parent": {"type": "contract", "name": "DaiEchidnaTest", "source_mapping": {"start": 335, "length": 2534, "filename_used": "/home/sencha/optimism-dai-bridge/contracts/test/DaiEchidnaTest.sol", "filename_relative": "contracts/test/DaiEchidnaTest.sol", "filename_absolute": "/home/sencha/optimism-dai-bridge/contracts/test/DaiEchidnaTest.sol", "filename_short": "contracts/test/DaiEchidnaTest.sol", "is_dependency": false, "lines": [14, 15, 16, 17, 18, 19, 20, 21, 22, 23, 24, 25, 26, 27, 28, 29, 30, 31, 32, 33, 34, 35, 36, 37, 38, 39, 40, 41, 42, 43, 44, 45, 46, 47, 48, 49, 50, 51, 52, 53, 54, 55, 56, 57, 58, 59, 60, 61, 62, 63, 64, 65, 66, 67, 68, 69, 70, 71, 72, 73, 74, 75, 76, 77], "starting_column": 1, "ending_column": 2}}, "signature": "mint(uint256)"}}}}], "description": "DaiEchidnaTest.mint(uint256) (contracts/test/DaiEchidnaTest.sol#39-46) uses a dangerous strict equality:\n\t- assert(bool)(dai.balanceOf(holder) == add(holderBalance,wad)) (contracts/test/DaiEchidnaTest.sol#44)\n", "markdown": "[DaiEchidnaTest.mint(uint256)](contracts/test/DaiEchidnaTest.sol#L39-L46) uses a dangerous strict equality:\n\t- [assert(bool)(dai.balanceOf(holder) == add(holderBalance,wad))](contracts/test/DaiEchidnaTest.sol#L44)\n", "first_markdown_element": "contracts/test/DaiEchidnaTest.sol#L39-L46", "id": "41e86f0045341210fd3498082ffd6b3edf2f94c4d0999243eff2918c36fb061e", "check": "incorrect-equality", "impact": "Medium", "confidence": "High"}, {"elements": [{"type": "function", "name": "transfer", "source_mapping": {"start": 1987, "length": 392, "filename_used": "/home/sencha/optimism-dai-bridge/contracts/test/DaiEchidnaTest.sol", "filename_relative": "contracts/test/DaiEchidnaTest.sol", "filename_absolute": "/home/sencha/optimism-dai-bridge/contracts/test/DaiEchidnaTest.sol", "filename_short": "contracts/test/DaiEchidnaTest.sol", "is_dependency": false, "lines": [59, 60, 61, 62, 63, 64, 65, 66], "starting_column": 5, "ending_column": 6}, "type_specific_fields": {"parent": {"type": "contract", "name": "DaiEchidnaTest", "source_mapping": {"start": 335, "length": 2534, "filename_used": "/home/sencha/optimism-dai-bridge/contracts/test/DaiEchidnaTest.sol", "filename_relative": "contracts/test/DaiEchidnaTest.sol", "filename_absolute": "/home/sencha/optimism-dai-bridge/contracts/test/DaiEchidnaTest.sol", "filename_short": "contracts/test/DaiEchidnaTest.sol", "is_dependency": false, "lines": [14, 15, 16, 17, 18, 19, 20, 21, 22, 23, 24, 25, 26, 27, 28, 29, 30, 31, 32, 33, 34, 35, 36, 37, 38, 39, 40, 41, 42, 43, 44, 45, 46, 47, 48, 49, 50, 51, 52, 53, 54, 55, 56, 57, 58, 59, 60, 61, 62, 63, 64, 65, 66, 67, 68, 69, 70, 71, 72, 73, 74, 75, 76, 77], "starting_column": 1, "ending_column": 2}}, "signature": "transfer(uint256)"}}, {"type": "node", "name": "assert(bool)(dai.balanceOf(address(this)) == sub(thisBalance,wad))", "source_mapping": {"start": 2245, "length": 61, "filename_used": "/home/sencha/optimism-dai-bridge/contracts/test/DaiEchidnaTest.sol", "filename_relative": "contracts/test/DaiEchidnaTest.sol", "filename_absolute": "/home/sencha/optimism-dai-bridge/contracts/test/DaiEchidnaTest.sol", "filename_short": "contracts/test/DaiEchidnaTest.sol", "is_dependency": false, "lines": [64], "starting_column": 9, "ending_column": 70}, "type_specific_fields": {"parent": {"type": "function", "name": "transfer", "source_mapping": {"start": 1987, "length": 392, "filename_used": "/home/sencha/optimism-dai-bridge/contracts/test/DaiEchidnaTest.sol", "filename_relative": "contracts/test/DaiEchidnaTest.sol", "filename_absolute": "/home/sencha/optimism-dai-bridge/contracts/test/DaiEchidnaTest.sol", "filename_short": "contracts/test/DaiEchidnaTest.sol", "is_dependency": false, "lines": [59, 60, 61, 62, 63, 64, 65, 66], "starting_column": 5, "ending_column": 6}, "type_specific_fields": {"parent": {"type": "contract", "name": "DaiEchidnaTest", "source_mapping": {"start": 335, "length": 2534, "filename_used": "/home/sencha/optimism-dai-bridge/contracts/test/DaiEchidnaTest.sol", "filename_relative": "contracts/test/DaiEchidnaTest.sol", "filename_absolute": "/home/sencha/optimism-dai-bridge/contracts/test/DaiEchidnaTest.sol", "filename_short": "contracts/test/DaiEchidnaTest.sol", "is_dependency": false, "lines": [14, 15, 16, 17, 18, 19, 20, 21, 22, 23, 24, 25, 26, 27, 28, 29, 30, 31, 32, 33, 34, 35, 36, 37, 38, 39, 40, 41, 42, 43, 44, 45, 46, 47, 48, 49, 50, 51, 52, 53, 54, 55, 56, 57, 58, 59, 60, 61, 62, 63, 64, 65, 66, 67, 68, 69, 70, 71, 72, 73, 74, 75, 76, 77], "starting_column": 1, "ending_column": 2}}, "signature": "transfer(uint256)"}}}}], "description": "DaiEchidnaTest.transfer(uint256) (contracts/test/DaiEchidnaTest.sol#59-66) uses a dangerous strict equality:\n\t- assert(bool)(dai.balanceOf(address(this)) == sub(thisBalance,wad)) (contracts/test/DaiEchidnaTest.sol#64)\n", "markdown": "[DaiEchidnaTest.transfer(uint256)](contracts/test/DaiEchidnaTest.sol#L59-L66) uses a dangerous strict equality:\n\t- [assert(bool)(dai.balanceOf(address(this)) == sub(thisBalance,wad))](contracts/test/DaiEchidnaTest.sol#L64)\n", "first_markdown_element": "contracts/test/DaiEchidnaTest.sol#L59-L66", "id": "a858f7f36e373d42f78e1c6ce0b80737cb3672c6efe5e31c1d55c1c764e223fa", "check": "incorrect-equality", "impact": "Medium", "confidence": "High"}, {"elements": [{"type": "function", "name": "transfer", "source_mapping": {"start": 1987, "length": 392, "filename_used": "/home/sencha/optimism-dai-bridge/contracts/test/DaiEchidnaTest.sol", "filename_relative": "contracts/test/DaiEchidnaTest.sol", "filename_absolute": "/home/sencha/optimism-dai-bridge/contracts/test/DaiEchidnaTest.sol", "filename_short": "contracts/test/DaiEchidnaTest.sol", "is_dependency": false, "lines": [59, 60, 61, 62, 63, 64, 65, 66], "starting_column": 5, "ending_column": 6}, "type_specific_fields": {"parent": {"type": "contract", "name": "DaiEchidnaTest", "source_mapping": {"start": 335, "length": 2534, "filename_used": "/home/sencha/optimism-dai-bridge/contracts/test/DaiEchidnaTest.sol", "filename_relative": "contracts/test/DaiEchidnaTest.sol", "filename_absolute": "/home/sencha/optimism-dai-bridge/contracts/test/DaiEchidnaTest.sol", "filename_short": "contracts/test/DaiEchidnaTest.sol", "is_dependency": false, "lines": [14, 15, 16, 17, 18, 19, 20, 21, 22, 23, 24, 25, 26, 27, 28, 29, 30, 31, 32, 33, 34, 35, 36, 37, 38, 39, 40, 41, 42, 43, 44, 45, 46, 47, 48, 49, 50, 51, 52, 53, 54, 55, 56, 57, 58, 59, 60, 61, 62, 63, 64, 65, 66, 67, 68, 69, 70, 71, 72, 73, 74, 75, 76, 77], "starting_column": 1, "ending_column": 2}}, "signature": "transfer(uint256)"}}, {"type": "node", "name": "assert(bool)(dai.balanceOf(holder) == add(holderBalance,wad))", "source_mapping": {"start": 2316, "length": 56, "filename_used": "/home/sencha/optimism-dai-bridge/contracts/test/DaiEchidnaTest.sol", "filename_relative": "contracts/test/DaiEchidnaTest.sol", "filename_absolute": "/home/sencha/optimism-dai-bridge/contracts/test/DaiEchidnaTest.sol", "filename_short": "contracts/test/DaiEchidnaTest.sol", "is_dependency": false, "lines": [65], "starting_column": 9, "ending_column": 65}, "type_specific_fields": {"parent": {"type": "function", "name": "transfer", "source_mapping": {"start": 1987, "length": 392, "filename_used": "/home/sencha/optimism-dai-bridge/contracts/test/DaiEchidnaTest.sol", "filename_relative": "contracts/test/DaiEchidnaTest.sol", "filename_absolute": "/home/sencha/optimism-dai-bridge/contracts/test/DaiEchidnaTest.sol", "filename_short": "contracts/test/DaiEchidnaTest.sol", "is_dependency": false, "lines": [59, 60, 61, 62, 63, 64, 65, 66], "starting_column": 5, "ending_column": 6}, "type_specific_fields": {"parent": {"type": "contract", "name": "DaiEchidnaTest", "source_mapping": {"start": 335, "length": 2534, "filename_used": "/home/sencha/optimism-dai-bridge/contracts/test/DaiEchidnaTest.sol", "filename_relative": "contracts/test/DaiEchidnaTest.sol", "filename_absolute": "/home/sencha/optimism-dai-bridge/contracts/test/DaiEchidnaTest.sol", "filename_short": "contracts/test/DaiEchidnaTest.sol", "is_dependency": false, "lines": [14, 15, 16, 17, 18, 19, 20, 21, 22, 23, 24, 25, 26, 27, 28, 29, 30, 31, 32, 33, 34, 35, 36, 37, 38, 39, 40, 41, 42, 43, 44, 45, 46, 47, 48, 49, 50, 51, 52, 53, 54, 55, 56, 57, 58, 59, 60, 61, 62, 63, 64, 65, 66, 67, 68, 69, 70, 71, 72, 73, 74, 75, 76, 77], "starting_column": 1, "ending_column": 2}}, "signature": "transfer(uint256)"}}}}], "description": "DaiEchidnaTest.transfer(uint256) (contracts/test/DaiEchidnaTest.sol#59-66) uses a dangerous strict equality:\n\t- assert(bool)(dai.balanceOf(holder) == add(holderBalance,wad)) (contracts/test/DaiEchidnaTest.sol#65)\n", "markdown": "[DaiEchidnaTest.transfer(uint256)](contracts/test/DaiEchidnaTest.sol#L59-L66) uses a dangerous strict equality:\n\t- [assert(bool)(dai.balanceOf(holder) == add(holderBalance,wad))](contracts/test/DaiEchidnaTest.sol#L65)\n", "first_markdown_element": "contracts/test/DaiEchidnaTest.sol#L59-L66", "id": "439ddee32a2182e37b4f7ec11425b4c7287a0cb943554cf7802a2f7d66c3b5d4", "check": "incorrect-equality", "impact": "Medium", "confidence": "High"}, {"elements": [{"type": "function", "name": "transfer", "source_mapping": {"start": 1987, "length": 392, "filename_used": "/home/sencha/optimism-dai-bridge/contracts/test/DaiEchidnaTest.sol", "filename_relative": "contracts/test/DaiEchidnaTest.sol", "filename_absolute": "/home/sencha/optimism-dai-bridge/contracts/test/DaiEchidnaTest.sol", "filename_short": "contracts/test/DaiEchidnaTest.sol", "is_dependency": false, "lines": [59, 60, 61, 62, 63, 64, 65, 66], "starting_column": 5, "ending_column": 6}, "type_specific_fields": {"parent": {"type": "contract", "name": "DaiEchidnaTest", "source_mapping": {"start": 335, "length": 2534, "filename_used": "/home/sencha/optimism-dai-bridge/contracts/test/DaiEchidnaTest.sol", "filename_relative": "contracts/test/DaiEchidnaTest.sol", "filename_absolute": "/home/sencha/optimism-dai-bridge/contracts/test/DaiEchidnaTest.sol", "filename_short": "contracts/test/DaiEchidnaTest.sol", "is_dependency": false, "lines": [14, 15, 16, 17, 18, 19, 20, 21, 22, 23, 24, 25, 26, 27, 28, 29, 30, 31, 32, 33, 34, 35, 36, 37, 38, 39, 40, 41, 42, 43, 44, 45, 46, 47, 48, 49, 50, 51, 52, 53, 54, 55, 56, 57, 58, 59, 60, 61, 62, 63, 64, 65, 66, 67, 68, 69, 70, 71, 72, 73, 74, 75, 76, 77], "starting_column": 1, "ending_column": 2}}, "signature": "transfer(uint256)"}}, {"type": "node", "name": "thisBalance == 0", "source_mapping": {"start": 2150, "length": 50, "filename_used": "/home/sencha/optimism-dai-bridge/contracts/test/DaiEchidnaTest.sol", "filename_relative": "contracts/test/DaiEchidnaTest.sol", "filename_absolute": "/home/sencha/optimism-dai-bridge/contracts/test/DaiEchidnaTest.sol", "filename_short": "contracts/test/DaiEchidnaTest.sol", "is_dependency": false, "lines": [62], "starting_column": 9, "ending_column": 59}, "type_specific_fields": {"parent": {"type": "function", "name": "transfer", "source_mapping": {"start": 1987, "length": 392, "filename_used": "/home/sencha/optimism-dai-bridge/contracts/test/DaiEchidnaTest.sol", "filename_relative": "contracts/test/DaiEchidnaTest.sol", "filename_absolute": "/home/sencha/optimism-dai-bridge/contracts/test/DaiEchidnaTest.sol", "filename_short": "contracts/test/DaiEchidnaTest.sol", "is_dependency": false, "lines": [59, 60, 61, 62, 63, 64, 65, 66], "starting_column": 5, "ending_column": 6}, "type_specific_fields": {"parent": {"type": "contract", "name": "DaiEchidnaTest", "source_mapping": {"start": 335, "length": 2534, "filename_used": "/home/sencha/optimism-dai-bridge/contracts/test/DaiEchidnaTest.sol", "filename_relative": "contracts/test/DaiEchidnaTest.sol", "filename_absolute": "/home/sencha/optimism-dai-bridge/contracts/test/DaiEchidnaTest.sol", "filename_short": "contracts/test/DaiEchidnaTest.sol", "is_dependency": false, "lines": [14, 15, 16, 17, 18, 19, 20, 21, 22, 23, 24, 25, 26, 27, 28, 29, 30, 31, 32, 33, 34, 35, 36, 37, 38, 39, 40, 41, 42, 43, 44, 45, 46, 47, 48, 49, 50, 51, 52, 53, 54, 55, 56, 57, 58, 59, 60, 61, 62, 63, 64, 65, 66, 67, 68, 69, 70, 71, 72, 73, 74, 75, 76, 77], "starting_column": 1, "ending_column": 2}}, "signature": "transfer(uint256)"}}}}], "description": "DaiEchidnaTest.transfer(uint256) (contracts/test/DaiEchidnaTest.sol#59-66) uses a dangerous strict equality:\n\t- thisBalance == 0 (contracts/test/DaiEchidnaTest.sol#62)\n", "markdown": "[DaiEchidnaTest.transfer(uint256)](contracts/test/DaiEchidnaTest.sol#L59-L66) uses a dangerous strict equality:\n\t- [thisBalance == 0](contracts/test/DaiEchidnaTest.sol#L62)\n", "first_markdown_element": "contracts/test/DaiEchidnaTest.sol#L59-L66", "id": "1e8e7442a0ac76fa83756d9662e5b10ea1899016694f22cd9e1bf07c142f70b7", "check": "incorrect-equality", "impact": "Medium", "confidence": "High"}, {"elements": [{"type": "function", "name": "transferFrom", "source_mapping": {"start": 2448, "length": 419, "filename_used": "/home/sencha/optimism-dai-bridge/contracts/test/DaiEchidnaTest.sol", "filename_relative": "contracts/test/DaiEchidnaTest.sol", "filename_absolute": "/home/sencha/optimism-dai-bridge/contracts/test/DaiEchidnaTest.sol", "filename_short": "contracts/test/DaiEchidnaTest.sol", "is_dependency": false, "lines": [69, 70, 71, 72, 73, 74, 75, 76], "starting_column": 5, "ending_column": 6}, "type_specific_fields": {"parent": {"type": "contract", "name": "DaiEchidnaTest", "source_mapping": {"start": 335, "length": 2534, "filename_used": "/home/sencha/optimism-dai-bridge/contracts/test/DaiEchidnaTest.sol", "filename_relative": "contracts/test/DaiEchidnaTest.sol", "filename_absolute": "/home/sencha/optimism-dai-bridge/contracts/test/DaiEchidnaTest.sol", "filename_short": "contracts/test/DaiEchidnaTest.sol", "is_dependency": false, "lines": [14, 15, 16, 17, 18, 19, 20, 21, 22, 23, 24, 25, 26, 27, 28, 29, 30, 31, 32, 33, 34, 35, 36, 37, 38, 39, 40, 41, 42, 43, 44, 45, 46, 47, 48, 49, 50, 51, 52, 53, 54, 55, 56, 57, 58, 59, 60, 61, 62, 63, 64, 65, 66, 67, 68, 69, 70, 71, 72, 73, 74, 75, 76, 77], "starting_column": 1, "ending_column": 2}}, "signature": "transferFrom(uint256)"}}, {"type": "node", "name": "assert(bool)(dai.balanceOf(holder) == sub(holderBalance,wad))", "source_mapping": {"start": 2733, "length": 56, "filename_used": "/home/sencha/optimism-dai-bridge/contracts/test/DaiEchidnaTest.sol", "filename_relative": "contracts/test/DaiEchidnaTest.sol", "filename_absolute": "/home/sencha/optimism-dai-bridge/contracts/test/DaiEchidnaTest.sol", "filename_short": "contracts/test/DaiEchidnaTest.sol", "is_dependency": false, "lines": [74], "starting_column": 9, "ending_column": 65}, "type_specific_fields": {"parent": {"type": "function", "name": "transferFrom", "source_mapping": {"start": 2448, "length": 419, "filename_used": "/home/sencha/optimism-dai-bridge/contracts/test/DaiEchidnaTest.sol", "filename_relative": "contracts/test/DaiEchidnaTest.sol", "filename_absolute": "/home/sencha/optimism-dai-bridge/contracts/test/DaiEchidnaTest.sol", "filename_short": "contracts/test/DaiEchidnaTest.sol", "is_dependency": false, "lines": [69, 70, 71, 72, 73, 74, 75, 76], "starting_column": 5, "ending_column": 6}, "type_specific_fields": {"parent": {"type": "contract", "name": "DaiEchidnaTest", "source_mapping": {"start": 335, "length": 2534, "filename_used": "/home/sencha/optimism-dai-bridge/contracts/test/DaiEchidnaTest.sol", "filename_relative": "contracts/test/DaiEchidnaTest.sol", "filename_absolute": "/home/sencha/optimism-dai-bridge/contracts/test/DaiEchidnaTest.sol", "filename_short": "contracts/test/DaiEchidnaTest.sol", "is_dependency": false, "lines": [14, 15, 16, 17, 18, 19, 20, 21, 22, 23, 24, 25, 26, 27, 28, 29, 30, 31, 32, 33, 34, 35, 36, 37, 38, 39, 40, 41, 42, 43, 44, 45, 46, 47, 48, 49, 50, 51, 52, 53, 54, 55, 56, 57, 58, 59, 60, 61, 62, 63, 64, 65, 66, 67, 68, 69, 70, 71, 72, 73, 74, 75, 76, 77], "starting_column": 1, "ending_column": 2}}, "signature": "transferFrom(uint256)"}}}}], "description": "DaiEchidnaTest.transferFrom(uint256) (contracts/test/DaiEchidnaTest.sol#69-76) uses a dangerous strict equality:\n\t- assert(bool)(dai.balanceOf(holder) == sub(holderBalance,wad)) (contracts/test/DaiEchidnaTest.sol#74)\n", "markdown": "[DaiEchidnaTest.transferFrom(uint256)](contracts/test/DaiEchidnaTest.sol#L69-L76) uses a dangerous strict equality:\n\t- [assert(bool)(dai.balanceOf(holder) == sub(holderBalance,wad))](contracts/test/DaiEchidnaTest.sol#L74)\n", "first_markdown_element": "contracts/test/DaiEchidnaTest.sol#L69-L76", "id": "236e27ec3c6f8e9ce208b2ff584ce7a4f6dd9438b4bc472d151e29fc60842561", "check": "incorrect-equality", "impact": "Medium", "confidence": "High"}, {"elements": [{"type": "function", "name": "transferFrom", "source_mapping": {"start": 2448, "length": 419, "filename_used": "/home/sencha/optimism-dai-bridge/contracts/test/DaiEchidnaTest.sol", "filename_relative": "contracts/test/DaiEchidnaTest.sol", "filename_absolute": "/home/sencha/optimism-dai-bridge/contracts/test/DaiEchidnaTest.sol", "filename_short": "contracts/test/DaiEchidnaTest.sol", "is_dependency": false, "lines": [69, 70, 71, 72, 73, 74, 75, 76], "starting_column": 5, "ending_column": 6}, "type_specific_fields": {"parent": {"type": "contract", "name": "DaiEchidnaTest", "source_mapping": {"start": 335, "length": 2534, "filename_used": "/home/sencha/optimism-dai-bridge/contracts/test/DaiEchidnaTest.sol", "filename_relative": "contracts/test/DaiEchidnaTest.sol", "filename_absolute": "/home/sencha/optimism-dai-bridge/contracts/test/DaiEchidnaTest.sol", "filename_short": "contracts/test/DaiEchidnaTest.sol", "is_dependency": false, "lines": [14, 15, 16, 17, 18, 19, 20, 21, 22, 23, 24, 25, 26, 27, 28, 29, 30, 31, 32, 33, 34, 35, 36, 37, 38, 39, 40, 41, 42, 43, 44, 45, 46, 47, 48, 49, 50, 51, 52, 53, 54, 55, 56, 57, 58, 59, 60, 61, 62, 63, 64, 65, 66, 67, 68, 69, 70, 71, 72, 73, 74, 75, 76, 77], "starting_column": 1, "ending_column": 2}}, "signature": "transferFrom(uint256)"}}, {"type": "node", "name": "assert(bool)(dai.balanceOf(address(this)) == add(thisBalance,wad))", "source_mapping": {"start": 2799, "length": 61, "filename_used": "/home/sencha/optimism-dai-bridge/contracts/test/DaiEchidnaTest.sol", "filename_relative": "contracts/test/DaiEchidnaTest.sol", "filename_absolute": "/home/sencha/optimism-dai-bridge/contracts/test/DaiEchidnaTest.sol", "filename_short": "contracts/test/DaiEchidnaTest.sol", "is_dependency": false, "lines": [75], "starting_column": 9, "ending_column": 70}, "type_specific_fields": {"parent": {"type": "function", "name": "transferFrom", "source_mapping": {"start": 2448, "length": 419, "filename_used": "/home/sencha/optimism-dai-bridge/contracts/test/DaiEchidnaTest.sol", "filename_relative": "contracts/test/DaiEchidnaTest.sol", "filename_absolute": "/home/sencha/optimism-dai-bridge/contracts/test/DaiEchidnaTest.sol", "filename_short": "contracts/test/DaiEchidnaTest.sol", "is_dependency": false, "lines": [69, 70, 71, 72, 73, 74, 75, 76], "starting_column": 5, "ending_column": 6}, "type_specific_fields": {"parent": {"type": "contract", "name": "DaiEchidnaTest", "source_mapping": {"start": 335, "length": 2534, "filename_used": "/home/sencha/optimism-dai-bridge/contracts/test/DaiEchidnaTest.sol", "filename_relative": "contracts/test/DaiEchidnaTest.sol", "filename_absolute": "/home/sencha/optimism-dai-bridge/contracts/test/DaiEchidnaTest.sol", "filename_short": "contracts/test/DaiEchidnaTest.sol", "is_dependency": false, "lines": [14, 15, 16, 17, 18, 19, 20, 21, 22, 23, 24, 25, 26, 27, 28, 29, 30, 31, 32, 33, 34, 35, 36, 37, 38, 39, 40, 41, 42, 43, 44, 45, 46, 47, 48, 49, 50, 51, 52, 53, 54, 55, 56, 57, 58, 59, 60, 61, 62, 63, 64, 65, 66, 67, 68, 69, 70, 71, 72, 73, 74, 75, 76, 77], "starting_column": 1, "ending_column": 2}}, "signature": "transferFrom(uint256)"}}}}], "description": "DaiEchidnaTest.transferFrom(uint256) (contracts/test/DaiEchidnaTest.sol#69-76) uses a dangerous strict equality:\n\t- assert(bool)(dai.balanceOf(address(this)) == add(thisBalance,wad)) (contracts/test/DaiEchidnaTest.sol#75)\n", "markdown": "[DaiEchidnaTest.transferFrom(uint256)](contracts/test/DaiEchidnaTest.sol#L69-L76) uses a dangerous strict equality:\n\t- [assert(bool)(dai.balanceOf(address(this)) == add(thisBalance,wad))](contracts/test/DaiEchidnaTest.sol#L75)\n", "first_markdown_element": "contracts/test/DaiEchidnaTest.sol#L69-L76", "id": "cf40a5eb0835ae20c7d01bd5e118309dc7648d9118a07ab7a53c386ad712f347", "check": "incorrect-equality", "impact": "Medium", "confidence": "High"}, {"elements": [{"type": "function", "name": "transferFrom", "source_mapping": {"start": 2448, "length": 419, "filename_used": "/home/sencha/optimism-dai-bridge/contracts/test/DaiEchidnaTest.sol", "filename_relative": "contracts/test/DaiEchidnaTest.sol", "filename_absolute": "/home/sencha/optimism-dai-bridge/contracts/test/DaiEchidnaTest.sol", "filename_short": "contracts/test/DaiEchidnaTest.sol", "is_dependency": false, "lines": [69, 70, 71, 72, 73, 74, 75, 76], "starting_column": 5, "ending_column": 6}, "type_specific_fields": {"parent": {"type": "contract", "name": "DaiEchidnaTest", "source_mapping": {"start": 335, "length": 2534, "filename_used": "/home/sencha/optimism-dai-bridge/contracts/test/DaiEchidnaTest.sol", "filename_relative": "contracts/test/DaiEchidnaTest.sol", "filename_absolute": "/home/sencha/optimism-dai-bridge/contracts/test/DaiEchidnaTest.sol", "filename_short": "contracts/test/DaiEchidnaTest.sol", "is_dependency": false, "lines": [14, 15, 16, 17, 18, 19, 20, 21, 22, 23, 24, 25, 26, 27, 28, 29, 30, 31, 32, 33, 34, 35, 36, 37, 38, 39, 40, 41, 42, 43, 44, 45, 46, 47, 48, 49, 50, 51, 52, 53, 54, 55, 56, 57, 58, 59, 60, 61, 62, 63, 64, 65, 66, 67, 68, 69, 70, 71, 72, 73, 74, 75, 76, 77], "starting_column": 1, "ending_column": 2}}, "signature": "transferFrom(uint256)"}}, {"type": "node", "name": "holderBalance == 0", "source_mapping": {"start": 2615, "length": 54, "filename_used": "/home/sencha/optimism-dai-bridge/contracts/test/DaiEchidnaTest.sol", "filename_relative": "contracts/test/DaiEchidnaTest.sol", "filename_absolute": "/home/sencha/optimism-dai-bridge/contracts/test/DaiEchidnaTest.sol", "filename_short": "contracts/test/DaiEchidnaTest.sol", "is_dependency": false, "lines": [72], "starting_column": 9, "ending_column": 63}, "type_specific_fields": {"parent": {"type": "function", "name": "transferFrom", "source_mapping": {"start": 2448, "length": 419, "filename_used": "/home/sencha/optimism-dai-bridge/contracts/test/DaiEchidnaTest.sol", "filename_relative": "contracts/test/DaiEchidnaTest.sol", "filename_absolute": "/home/sencha/optimism-dai-bridge/contracts/test/DaiEchidnaTest.sol", "filename_short": "contracts/test/DaiEchidnaTest.sol", "is_dependency": false, "lines": [69, 70, 71, 72, 73, 74, 75, 76], "starting_column": 5, "ending_column": 6}, "type_specific_fields": {"parent": {"type": "contract", "name": "DaiEchidnaTest", "source_mapping": {"start": 335, "length": 2534, "filename_used": "/home/sencha/optimism-dai-bridge/contracts/test/DaiEchidnaTest.sol", "filename_relative": "contracts/test/DaiEchidnaTest.sol", "filename_absolute": "/home/sencha/optimism-dai-bridge/contracts/test/DaiEchidnaTest.sol", "filename_short": "contracts/test/DaiEchidnaTest.sol", "is_dependency": false, "lines": [14, 15, 16, 17, 18, 19, 20, 21, 22, 23, 24, 25, 26, 27, 28, 29, 30, 31, 32, 33, 34, 35, 36, 37, 38, 39, 40, 41, 42, 43, 44, 45, 46, 47, 48, 49, 50, 51, 52, 53, 54, 55, 56, 57, 58, 59, 60, 61, 62, 63, 64, 65, 66, 67, 68, 69, 70, 71, 72, 73, 74, 75, 76, 77], "starting_column": 1, "ending_column": 2}}, "signature": "transferFrom(uint256)"}}}}], "description": "DaiEchidnaTest.transferFrom(uint256) (contracts/test/DaiEchidnaTest.sol#69-76) uses a dangerous strict equality:\n\t- holderBalance == 0 (contracts/test/DaiEchidnaTest.sol#72)\n", "markdown": "[DaiEchidnaTest.transferFrom(uint256)](contracts/test/DaiEchidnaTest.sol#L69-L76) uses a dangerous strict equality:\n\t- [holderBalance == 0](contracts/test/DaiEchidnaTest.sol#L72)\n", "first_markdown_element": "contracts/test/DaiEchidnaTest.sol#L69-L76", "id": "ff46ee0c344a7433a75e05bf4ed3a473836fb66790909462ec692afe8b690857", "check": "incorrect-equality", "impact": "Medium", "confidence": "High"}, {"elements": [{"type": "function", "name": "deposit", "source_mapping": {"start": 19394, "length": 606, "filename_used": "/home/sencha/optimism-dai-bridge/contracts/test/EscrowEchidnaTest.sol", "filename_relative": "contracts/test/EscrowEchidnaTest.sol", "filename_absolute": "/home/sencha/optimism-dai-bridge/contracts/test/EscrowEchidnaTest.sol", "filename_short": "contracts/test/EscrowEchidnaTest.sol", "is_dependency": false, "lines": [87, 88, 89, 90, 91, 92, 93, 94, 95, 96, 97], "starting_column": 5, "ending_column": 6}, "type_specific_fields": {"parent": {"type": "contract", "name": "EscrowEchidnaTest", "source_mapping": {"start": 18157, "length": 1845, "filename_used": "/home/sencha/optimism-dai-bridge/contracts/test/EscrowEchidnaTest.sol", "filename_relative": "contracts/test/EscrowEchidnaTest.sol", "filename_absolute": "/home/sencha/optimism-dai-bridge/contracts/test/EscrowEchidnaTest.sol", "filename_short": "contracts/test/EscrowEchidnaTest.sol", "is_dependency": false, "lines": [49, 50, 51, 52, 53, 54, 55, 56, 57, 58, 59, 60, 61, 62, 63, 64, 65, 66, 67, 68, 69, 70, 71, 72, 73, 74, 75, 76, 77, 78, 79, 80, 81, 82, 83, 84, 85, 86, 87, 88, 89, 90, 91, 92, 93, 94, 95, 96, 97, 98], "starting_column": 1, "ending_column": 2}}, "signature": "deposit(uint256)"}}, {"type": "node", "name": "assert(bool)(DaiLike(dai).balanceOf(address(this)) == add(thisBalance,wad))", "source_mapping": {"start": 19732, "length": 70, "filename_used": "/home/sencha/optimism-dai-bridge/contracts/test/EscrowEchidnaTest.sol", "filename_relative": "contracts/test/EscrowEchidnaTest.sol", "filename_absolute": "/home/sencha/optimism-dai-bridge/contracts/test/EscrowEchidnaTest.sol", "filename_short": "contracts/test/EscrowEchidnaTest.sol", "is_dependency": false, "lines": [93], "starting_column": 9, "ending_column": 79}, "type_specific_fields": {"parent": {"type": "function", "name": "deposit", "source_mapping": {"start": 19394, "length": 606, "filename_used": "/home/sencha/optimism-dai-bridge/contracts/test/EscrowEchidnaTest.sol", "filename_relative": "contracts/test/EscrowEchidnaTest.sol", "filename_absolute": "/home/sencha/optimism-dai-bridge/contracts/test/EscrowEchidnaTest.sol", "filename_short": "contracts/test/EscrowEchidnaTest.sol", "is_dependency": false, "lines": [87, 88, 89, 90, 91, 92, 93, 94, 95, 96, 97], "starting_column": 5, "ending_column": 6}, "type_specific_fields": {"parent": {"type": "contract", "name": "EscrowEchidnaTest", "source_mapping": {"start": 18157, "length": 1845, "filename_used": "/home/sencha/optimism-dai-bridge/contracts/test/EscrowEchidnaTest.sol", "filename_relative": "contracts/test/EscrowEchidnaTest.sol", "filename_absolute": "/home/sencha/optimism-dai-bridge/contracts/test/EscrowEchidnaTest.sol", "filename_short": "contracts/test/EscrowEchidnaTest.sol", "is_dependency": false, "lines": [49, 50, 51, 52, 53, 54, 55, 56, 57, 58, 59, 60, 61, 62, 63, 64, 65, 66, 67, 68, 69, 70, 71, 72, 73, 74, 75, 76, 77, 78, 79, 80, 81, 82, 83, 84, 85, 86, 87, 88, 89, 90, 91, 92, 93, 94, 95, 96, 97, 98], "starting_column": 1, "ending_column": 2}}, "signature": "deposit(uint256)"}}}}], "description": "EscrowEchidnaTest.deposit(uint256) (contracts/test/EscrowEchidnaTest.sol#87-97) uses a dangerous strict equality:\n\t- assert(bool)(DaiLike(dai).balanceOf(address(this)) == add(thisBalance,wad)) (contracts/test/EscrowEchidnaTest.sol#93)\n", "markdown": "[EscrowEchidnaTest.deposit(uint256)](contracts/test/EscrowEchidnaTest.sol#L87-L97) uses a dangerous strict equality:\n\t- [assert(bool)(DaiLike(dai).balanceOf(address(this)) == add(thisBalance,wad))](contracts/test/EscrowEchidnaTest.sol#L93)\n", "first_markdown_element": "contracts/test/EscrowEchidnaTest.sol#L87-L97", "id": "0e8ae55ef8d89710bce439f246fbac503cf74e2b9315c3b8379b5f3fe73f82cf", "check": "incorrect-equality", "impact": "Medium", "confidence": "High"}, {"elements": [{"type": "function", "name": "deposit", "source_mapping": {"start": 19394, "length": 606, "filename_used": "/home/sencha/optimism-dai-bridge/contracts/test/EscrowEchidnaTest.sol", "filename_relative": "contracts/test/EscrowEchidnaTest.sol", "filename_absolute": "/home/sencha/optimism-dai-bridge/contracts/test/EscrowEchidnaTest.sol", "filename_short": "contracts/test/EscrowEchidnaTest.sol", "is_dependency": false, "lines": [87, 88, 89, 90, 91, 92, 93, 94, 95, 96, 97], "starting_column": 5, "ending_column": 6}, "type_specific_fields": {"parent": {"type": "contract", "name": "EscrowEchidnaTest", "source_mapping": {"start": 18157, "length": 1845, "filename_used": "/home/sencha/optimism-dai-bridge/contracts/test/EscrowEchidnaTest.sol", "filename_relative": "contracts/test/EscrowEchidnaTest.sol", "filename_absolute": "/home/sencha/optimism-dai-bridge/contracts/test/EscrowEchidnaTest.sol", "filename_short": "contracts/test/EscrowEchidnaTest.sol", "is_dependency": false, "lines": [49, 50, 51, 52, 53, 54, 55, 56, 57, 58, 59, 60, 61, 62, 63, 64, 65, 66, 67, 68, 69, 70, 71, 72, 73, 74, 75, 76, 77, 78, 79, 80, 81, 82, 83, 84, 85, 86, 87, 88, 89, 90, 91, 92, 93, 94, 95, 96, 97, 98], "starting_column": 1, "ending_column": 2}}, "signature": "deposit(uint256)"}}, {"type": "node", "name": "assert(bool)(DaiLike(dai).balanceOf(address(escrow)) == add(escrowBalance,wad))", "source_mapping": {"start": 19840, "length": 74, "filename_used": "/home/sencha/optimism-dai-bridge/contracts/test/EscrowEchidnaTest.sol", "filename_relative": "contracts/test/EscrowEchidnaTest.sol", "filename_absolute": "/home/sencha/optimism-dai-bridge/contracts/test/EscrowEchidnaTest.sol", "filename_short": "contracts/test/EscrowEchidnaTest.sol", "is_dependency": false, "lines": [95], "starting_column": 9, "ending_column": 83}, "type_specific_fields": {"parent": {"type": "function", "name": "deposit", "source_mapping": {"start": 19394, "length": 606, "filename_used": "/home/sencha/optimism-dai-bridge/contracts/test/EscrowEchidnaTest.sol", "filename_relative": "contracts/test/EscrowEchidnaTest.sol", "filename_absolute": "/home/sencha/optimism-dai-bridge/contracts/test/EscrowEchidnaTest.sol", "filename_short": "contracts/test/EscrowEchidnaTest.sol", "is_dependency": false, "lines": [87, 88, 89, 90, 91, 92, 93, 94, 95, 96, 97], "starting_column": 5, "ending_column": 6}, "type_specific_fields": {"parent": {"type": "contract", "name": "EscrowEchidnaTest", "source_mapping": {"start": 18157, "length": 1845, "filename_used": "/home/sencha/optimism-dai-bridge/contracts/test/EscrowEchidnaTest.sol", "filename_relative": "contracts/test/EscrowEchidnaTest.sol", "filename_absolute": "/home/sencha/optimism-dai-bridge/contracts/test/EscrowEchidnaTest.sol", "filename_short": "contracts/test/EscrowEchidnaTest.sol", "is_dependency": false, "lines": [49, 50, 51, 52, 53, 54, 55, 56, 57, 58, 59, 60, 61, 62, 63, 64, 65, 66, 67, 68, 69, 70, 71, 72, 73, 74, 75, 76, 77, 78, 79, 80, 81, 82, 83, 84, 85, 86, 87, 88, 89, 90, 91, 92, 93, 94, 95, 96, 97, 98], "starting_column": 1, "ending_column": 2}}, "signature": "deposit(uint256)"}}}}], "description": "EscrowEchidnaTest.deposit(uint256) (contracts/test/EscrowEchidnaTest.sol#87-97) uses a dangerous strict equality:\n\t- assert(bool)(DaiLike(dai).balanceOf(address(escrow)) == add(escrowBalance,wad)) (contracts/test/EscrowEchidnaTest.sol#95)\n", "markdown": "[EscrowEchidnaTest.deposit(uint256)](contracts/test/EscrowEchidnaTest.sol#L87-L97) uses a dangerous strict equality:\n\t- [assert(bool)(DaiLike(dai).balanceOf(address(escrow)) == add(escrowBalance,wad))](contracts/test/EscrowEchidnaTest.sol#L95)\n", "first_markdown_element": "contracts/test/EscrowEchidnaTest.sol#L87-L97", "id": "9b8b9044431c269fdd99e1f078c951ade1d30cbfd18f11814f69a3bde40c81a9", "check": "incorrect-equality", "impact": "Medium", "confidence": "High"}, {"elements": [{"type": "function", "name": "constructor", "source_mapping": {"start": 18512, "length": 506, "filename_used": "/home/sencha/optimism-dai-bridge/contracts/test/EscrowEchidnaTest.sol", "filename_relative": "contracts/test/EscrowEchidnaTest.sol", "filename_absolute": "/home/sencha/optimism-dai-bridge/contracts/test/EscrowEchidnaTest.sol", "filename_short": "contracts/test/EscrowEchidnaTest.sol", "is_dependency": false, "lines": [63, 64, 65, 66, 67, 68, 69, 70, 71, 72, 73, 74], "starting_column": 5, "ending_column": 6}, "type_specific_fields": {"parent": {"type": "contract", "name": "EscrowEchidnaTest", "source_mapping": {"start": 18157, "length": 1845, "filename_used": "/home/sencha/optimism-dai-bridge/contracts/test/EscrowEchidnaTest.sol", "filename_relative": "contracts/test/EscrowEchidnaTest.sol", "filename_absolute": "/home/sencha/optimism-dai-bridge/contracts/test/EscrowEchidnaTest.sol", "filename_short": "contracts/test/EscrowEchidnaTest.sol", "is_dependency": false, "lines": [49, 50, 51, 52, 53, 54, 55, 56, 57, 58, 59, 60, 61, 62, 63, 64, 65, 66, 67, 68, 69, 70, 71, 72, 73, 74, 75, 76, 77, 78, 79, 80, 81, 82, 83, 84, 85, 86, 87, 88, 89, 90, 91, 92, 93, 94, 95, 96, 97, 98], "starting_column": 1, "ending_column": 2}}, "signature": "constructor()"}}, {"type": "node", "name": "dai = create.deploy()", "source_mapping": {"start": 18568, "length": 21, "filename_used": "/home/sencha/optimism-dai-bridge/contracts/test/EscrowEchidnaTest.sol", "filename_relative": "contracts/test/EscrowEchidnaTest.sol", "filename_absolute": "/home/sencha/optimism-dai-bridge/contracts/test/EscrowEchidnaTest.sol", "filename_short": "contracts/test/EscrowEchidnaTest.sol", "is_dependency": false, "lines": [65], "starting_column": 9, "ending_column": 30}, "type_specific_fields": {"parent": {"type": "function", "name": "constructor", "source_mapping": {"start": 18512, "length": 506, "filename_used": "/home/sencha/optimism-dai-bridge/contracts/test/EscrowEchidnaTest.sol", "filename_relative": "contracts/test/EscrowEchidnaTest.sol", "filename_absolute": "/home/sencha/optimism-dai-bridge/contracts/test/EscrowEchidnaTest.sol", "filename_short": "contracts/test/EscrowEchidnaTest.sol", "is_dependency": false, "lines": [63, 64, 65, 66, 67, 68, 69, 70, 71, 72, 73, 74], "starting_column": 5, "ending_column": 6}, "type_specific_fields": {"parent": {"type": "contract", "name": "EscrowEchidnaTest", "source_mapping": {"start": 18157, "length": 1845, "filename_used": "/home/sencha/optimism-dai-bridge/contracts/test/EscrowEchidnaTest.sol", "filename_relative": "contracts/test/EscrowEchidnaTest.sol", "filename_absolute": "/home/sencha/optimism-dai-bridge/contracts/test/EscrowEchidnaTest.sol", "filename_short": "contracts/test/EscrowEchidnaTest.sol", "is_dependency": false, "lines": [49, 50, 51, 52, 53, 54, 55, 56, 57, 58, 59, 60, 61, 62, 63, 64, 65, 66, 67, 68, 69, 70, 71, 72, 73, 74, 75, 76, 77, 78, 79, 80, 81, 82, 83, 84, 85, 86, 87, 88, 89, 90, 91, 92, 93, 94, 95, 96, 97, 98], "starting_column": 1, "ending_column": 2}}, "signature": "constructor()"}}}, "additional_fields": {"underlying_type": "external_calls"}}, {"type": "node", "name": "dai = create.deploy()", "source_mapping": {"start": 18568, "length": 21, "filename_used": "/home/sencha/optimism-dai-bridge/contracts/test/EscrowEchidnaTest.sol", "filename_relative": "contracts/test/EscrowEchidnaTest.sol", "filename_absolute": "/home/sencha/optimism-dai-bridge/contracts/test/EscrowEchidnaTest.sol", "filename_short": "contracts/test/EscrowEchidnaTest.sol", "is_dependency": false, "lines": [65], "starting_column": 9, "ending_column": 30}, "type_specific_fields": {"parent": {"type": "function", "name": "constructor", "source_mapping": {"start": 18512, "length": 506, "filename_used": "/home/sencha/optimism-dai-bridge/contracts/test/EscrowEchidnaTest.sol", "filename_relative": "contracts/test/EscrowEchidnaTest.sol", "filename_absolute": "/home/sencha/optimism-dai-bridge/contracts/test/EscrowEchidnaTest.sol", "filename_short": "contracts/test/EscrowEchidnaTest.sol", "is_dependency": false, "lines": [63, 64, 65, 66, 67, 68, 69, 70, 71, 72, 73, 74], "starting_column": 5, "ending_column": 6}, "type_specific_fields": {"parent": {"type": "contract", "name": "EscrowEchidnaTest", "source_mapping": {"start": 18157, "length": 1845, "filename_used": "/home/sencha/optimism-dai-bridge/contracts/test/EscrowEchidnaTest.sol", "filename_relative": "contracts/test/EscrowEchidnaTest.sol", "filename_absolute": "/home/sencha/optimism-dai-bridge/contracts/test/EscrowEchidnaTest.sol", "filename_short": "contracts/test/EscrowEchidnaTest.sol", "is_dependency": false, "lines": [49, 50, 51, 52, 53, 54, 55, 56, 57, 58, 59, 60, 61, 62, 63, 64, 65, 66, 67, 68, 69, 70, 71, 72, 73, 74, 75, 76, 77, 78, 79, 80, 81, 82, 83, 84, 85, 86, 87, 88, 89, 90, 91, 92, 93, 94, 95, 96, 97, 98], "starting_column": 1, "ending_column": 2}}, "signature": "constructor()"}}}, "additional_fields": {"underlying_type": "external_calls_sending_eth"}}, {"type": "node", "name": "escrow = new L1Escrow()", "source_mapping": {"start": 18625, "length": 23, "filename_used": "/home/sencha/optimism-dai-bridge/contracts/test/EscrowEchidnaTest.sol", "filename_relative": "contracts/test/EscrowEchidnaTest.sol", "filename_absolute": "/home/sencha/optimism-dai-bridge/contracts/test/EscrowEchidnaTest.sol", "filename_short": "contracts/test/EscrowEchidnaTest.sol", "is_dependency": false, "lines": [67], "starting_column": 9, "ending_column": 32}, "type_specific_fields": {"parent": {"type": "function", "name": "constructor", "source_mapping": {"start": 18512, "length": 506, "filename_used": "/home/sencha/optimism-dai-bridge/contracts/test/EscrowEchidnaTest.sol", "filename_relative": "contracts/test/EscrowEchidnaTest.sol", "filename_absolute": "/home/sencha/optimism-dai-bridge/contracts/test/EscrowEchidnaTest.sol", "filename_short": "contracts/test/EscrowEchidnaTest.sol", "is_dependency": false, "lines": [63, 64, 65, 66, 67, 68, 69, 70, 71, 72, 73, 74], "starting_column": 5, "ending_column": 6}, "type_specific_fields": {"parent": {"type": "contract", "name": "EscrowEchidnaTest", "source_mapping": {"start": 18157, "length": 1845, "filename_used": "/home/sencha/optimism-dai-bridge/contracts/test/EscrowEchidnaTest.sol", "filename_relative": "contracts/test/EscrowEchidnaTest.sol", "filename_absolute": "/home/sencha/optimism-dai-bridge/contracts/test/EscrowEchidnaTest.sol", "filename_short": "contracts/test/EscrowEchidnaTest.sol", "is_dependency": false, "lines": [49, 50, 51, 52, 53, 54, 55, 56, 57, 58, 59, 60, 61, 62, 63, 64, 65, 66, 67, 68, 69, 70, 71, 72, 73, 74, 75, 76, 77, 78, 79, 80, 81, 82, 83, 84, 85, 86, 87, 88, 89, 90, 91, 92, 93, 94, 95, 96, 97, 98], "starting_column": 1, "ending_column": 2}}, "signature": "constructor()"}}}, "additional_fields": {"underlying_type": "variables_written", "variable_name": "escrow"}}, {"type": "node", "name": "gate1 = new L1Gateway(TokenLike(dai),address(gate2),address(messenger),address(escrow))", "source_mapping": {"start": 18765, "length": 90, "filename_used": "/home/sencha/optimism-dai-bridge/contracts/test/EscrowEchidnaTest.sol", "filename_relative": "contracts/test/EscrowEchidnaTest.sol", "filename_absolute": "/home/sencha/optimism-dai-bridge/contracts/test/EscrowEchidnaTest.sol", "filename_short": "contracts/test/EscrowEchidnaTest.sol", "is_dependency": false, "lines": [70], "starting_column": 9, "ending_column": 99}, "type_specific_fields": {"parent": {"type": "function", "name": "constructor", "source_mapping": {"start": 18512, "length": 506, "filename_used": "/home/sencha/optimism-dai-bridge/contracts/test/EscrowEchidnaTest.sol", "filename_relative": "contracts/test/EscrowEchidnaTest.sol", "filename_absolute": "/home/sencha/optimism-dai-bridge/contracts/test/EscrowEchidnaTest.sol", "filename_short": "contracts/test/EscrowEchidnaTest.sol", "is_dependency": false, "lines": [63, 64, 65, 66, 67, 68, 69, 70, 71, 72, 73, 74], "starting_column": 5, "ending_column": 6}, "type_specific_fields": {"parent": {"type": "contract", "name": "EscrowEchidnaTest", "source_mapping": {"start": 18157, "length": 1845, "filename_used": "/home/sencha/optimism-dai-bridge/contracts/test/EscrowEchidnaTest.sol", "filename_relative": "contracts/test/EscrowEchidnaTest.sol", "filename_absolute": "/home/sencha/optimism-dai-bridge/contracts/test/EscrowEchidnaTest.sol", "filename_short": "contracts/test/EscrowEchidnaTest.sol", "is_dependency": false, "lines": [49, 50, 51, 52, 53, 54, 55, 56, 57, 58, 59, 60, 61, 62, 63, 64, 65, 66, 67, 68, 69, 70, 71, 72, 73, 74, 75, 76, 77, 78, 79, 80, 81, 82, 83, 84, 85, 86, 87, 88, 89, 90, 91, 92, 93, 94, 95, 96, 97, 98], "starting_column": 1, "ending_column": 2}}, "signature": "constructor()"}}}, "additional_fields": {"underlying_type": "variables_written", "variable_name": "gate1"}}, {"type": "node", "name": "gate2 = new L2Gateway(address(messenger),address(oDai))", "source_mapping": {"start": 18699, "length": 56, "filename_used": "/home/sencha/optimism-dai-bridge/contracts/test/EscrowEchidnaTest.sol", "filename_relative": "contracts/test/EscrowEchidnaTest.sol", "filename_absolute": "/home/sencha/optimism-dai-bridge/contracts/test/EscrowEchidnaTest.sol", "filename_short": "contracts/test/EscrowEchidnaTest.sol", "is_dependency": false, "lines": [69], "starting_column": 9, "ending_column": 65}, "type_specific_fields": {"parent": {"type": "function", "name": "constructor", "source_mapping": {"start": 18512, "length": 506, "filename_used": "/home/sencha/optimism-dai-bridge/contracts/test/EscrowEchidnaTest.sol", "filename_relative": "contracts/test/EscrowEchidnaTest.sol", "filename_absolute": "/home/sencha/optimism-dai-bridge/contracts/test/EscrowEchidnaTest.sol", "filename_short": "contracts/test/EscrowEchidnaTest.sol", "is_dependency": false, "lines": [63, 64, 65, 66, 67, 68, 69, 70, 71, 72, 73, 74], "starting_column": 5, "ending_column": 6}, "type_specific_fields": {"parent": {"type": "contract", "name": "EscrowEchidnaTest", "source_mapping": {"start": 18157, "length": 1845, "filename_used": "/home/sencha/optimism-dai-bridge/contracts/test/EscrowEchidnaTest.sol", "filename_relative": "contracts/test/EscrowEchidnaTest.sol", "filename_absolute": "/home/sencha/optimism-dai-bridge/contracts/test/EscrowEchidnaTest.sol", "filename_short": "contracts/test/EscrowEchidnaTest.sol", "is_dependency": false, "lines": [49, 50, 51, 52, 53, 54, 55, 56, 57, 58, 59, 60, 61, 62, 63, 64, 65, 66, 67, 68, 69, 70, 71, 72, 73, 74, 75, 76, 77, 78, 79, 80, 81, 82, 83, 84, 85, 86, 87, 88, 89, 90, 91, 92, 93, 94, 95, 96, 97, 98], "starting_column": 1, "ending_column": 2}}, "signature": "constructor()"}}}, "additional_fields": {"underlying_type": "variables_written", "variable_name": "gate2"}}, {"type": "node", "name": "messenger = new MockMessenger()", "source_mapping": {"start": 18658, "length": 31, "filename_used": "/home/sencha/optimism-dai-bridge/contracts/test/EscrowEchidnaTest.sol", "filename_relative": "contracts/test/EscrowEchidnaTest.sol", "filename_absolute": "/home/sencha/optimism-dai-bridge/contracts/test/EscrowEchidnaTest.sol", "filename_short": "contracts/test/EscrowEchidnaTest.sol", "is_dependency": false, "lines": [68], "starting_column": 9, "ending_column": 40}, "type_specific_fields": {"parent": {"type": "function", "name": "constructor", "source_mapping": {"start": 18512, "length": 506, "filename_used": "/home/sencha/optimism-dai-bridge/contracts/test/EscrowEchidnaTest.sol", "filename_relative": "contracts/test/EscrowEchidnaTest.sol", "filename_absolute": "/home/sencha/optimism-dai-bridge/contracts/test/EscrowEchidnaTest.sol", "filename_short": "contracts/test/EscrowEchidnaTest.sol", "is_dependency": false, "lines": [63, 64, 65, 66, 67, 68, 69, 70, 71, 72, 73, 74], "starting_column": 5, "ending_column": 6}, "type_specific_fields": {"parent": {"type": "contract", "name": "EscrowEchidnaTest", "source_mapping": {"start": 18157, "length": 1845, "filename_used": "/home/sencha/optimism-dai-bridge/contracts/test/EscrowEchidnaTest.sol", "filename_relative": "contracts/test/EscrowEchidnaTest.sol", "filename_absolute": "/home/sencha/optimism-dai-bridge/contracts/test/EscrowEchidnaTest.sol", "filename_short": "contracts/test/EscrowEchidnaTest.sol", "is_dependency": false, "lines": [49, 50, 51, 52, 53, 54, 55, 56, 57, 58, 59, 60, 61, 62, 63, 64, 65, 66, 67, 68, 69, 70, 71, 72, 73, 74, 75, 76, 77, 78, 79, 80, 81, 82, 83, 84, 85, 86, 87, 88, 89, 90, 91, 92, 93, 94, 95, 96, 97, 98], "starting_column": 1, "ending_column": 2}}, "signature": "constructor()"}}}, "additional_fields": {"underlying_type": "variables_written", "variable_name": "messenger"}}, {"type": "node", "name": "oDai = new Dai()", "source_mapping": {"start": 18599, "length": 16, "filename_used": "/home/sencha/optimism-dai-bridge/contracts/test/EscrowEchidnaTest.sol", "filename_relative": "contracts/test/EscrowEchidnaTest.sol", "filename_absolute": "/home/sencha/optimism-dai-bridge/contracts/test/EscrowEchidnaTest.sol", "filename_short": "contracts/test/EscrowEchidnaTest.sol", "is_dependency": false, "lines": [66], "starting_column": 9, "ending_column": 25}, "type_specific_fields": {"parent": {"type": "function", "name": "constructor", "source_mapping": {"start": 18512, "length": 506, "filename_used": "/home/sencha/optimism-dai-bridge/contracts/test/EscrowEchidnaTest.sol", "filename_relative": "contracts/test/EscrowEchidnaTest.sol", "filename_absolute": "/home/sencha/optimism-dai-bridge/contracts/test/EscrowEchidnaTest.sol", "filename_short": "contracts/test/EscrowEchidnaTest.sol", "is_dependency": false, "lines": [63, 64, 65, 66, 67, 68, 69, 70, 71, 72, 73, 74], "starting_column": 5, "ending_column": 6}, "type_specific_fields": {"parent": {"type": "contract", "name": "EscrowEchidnaTest", "source_mapping": {"start": 18157, "length": 1845, "filename_used": "/home/sencha/optimism-dai-bridge/contracts/test/EscrowEchidnaTest.sol", "filename_relative": "contracts/test/EscrowEchidnaTest.sol", "filename_absolute": "/home/sencha/optimism-dai-bridge/contracts/test/EscrowEchidnaTest.sol", "filename_short": "contracts/test/EscrowEchidnaTest.sol", "is_dependency": false, "lines": [49, 50, 51, 52, 53, 54, 55, 56, 57, 58, 59, 60, 61, 62, 63, 64, 65, 66, 67, 68, 69, 70, 71, 72, 73, 74, 75, 76, 77, 78, 79, 80, 81, 82, 83, 84, 85, 86, 87, 88, 89, 90, 91, 92, 93, 94, 95, 96, 97, 98], "starting_column": 1, "ending_column": 2}}, "signature": "constructor()"}}}, "additional_fields": {"underlying_type": "variables_written", "variable_name": "oDai"}}], "description": "Reentrancy in EscrowEchidnaTest.constructor() (contracts/test/EscrowEchidnaTest.sol#63-74):\n\tExternal calls:\n\t- dai = create.deploy() (contracts/test/EscrowEchidnaTest.sol#65)\n\tState variables written after the call(s):\n\t- escrow = new L1Escrow() (contracts/test/EscrowEchidnaTest.sol#67)\n\t- gate1 = new L1Gateway(TokenLike(dai),address(gate2),address(messenger),address(escrow)) (contracts/test/EscrowEchidnaTest.sol#70)\n\t- gate2 = new L2Gateway(address(messenger),address(oDai)) (contracts/test/EscrowEchidnaTest.sol#69)\n\t- messenger = new MockMessenger() (contracts/test/EscrowEchidnaTest.sol#68)\n\t- oDai = new Dai() (contracts/test/EscrowEchidnaTest.sol#66)\n", "markdown": "Reentrancy in [EscrowEchidnaTest.constructor()](contracts/test/EscrowEchidnaTest.sol#L63-L74):\n\tExternal calls:\n\t- [dai = create.deploy()](contracts/test/EscrowEchidnaTest.sol#L65)\n\tState variables written after the call(s):\n\t- [escrow = new L1Escrow()](contracts/test/EscrowEchidnaTest.sol#L67)\n\t- [gate1 = new L1Gateway(TokenLike(dai),address(gate2),address(messenger),address(escrow))](contracts/test/EscrowEchidnaTest.sol#L70)\n\t- [gate2 = new L2Gateway(address(messenger),address(oDai))](contracts/test/EscrowEchidnaTest.sol#L69)\n\t- [messenger = new MockMessenger()](contracts/test/EscrowEchidnaTest.sol#L68)\n\t- [oDai = new Dai()](contracts/test/EscrowEchidnaTest.sol#L66)\n", "first_markdown_element": "contracts/test/EscrowEchidnaTest.sol#L63-L74", "id": "4b690f6251e6ef77eadfa415a398733b6e16c4aff5564ebc6fa01a252d111a69", "check": "reentrancy-benign", "impact": "Low", "confidence": "Medium"}, {"elements": [{"type": "function", "name": "permit", "source_mapping": {"start": 6015, "length": 794, "filename_used": "/home/sencha/optimism-dai-bridge/contracts/l2/dai.sol", "filename_relative": "contracts/l2/dai.sol", "filename_absolute": "/home/sencha/optimism-dai-bridge/contracts/l2/dai.sol", "filename_short": "contracts/l2/dai.sol", "is_dependency": false, "lines": [184, 185, 186, 187, 188, 189, 190, 191, 192, 193, 194, 195, 196, 197, 198, 199, 200, 201, 202, 203, 204, 205, 206, 207, 208], "starting_column": 3, "ending_column": 4}, "type_specific_fields": {"parent": {"type": "contract", "name": "Dai", "source_mapping": {"start": 857, "length": 5954, "filename_used": "/home/sencha/optimism-dai-bridge/contracts/l2/dai.sol", "filename_relative": "contracts/l2/dai.sol", "filename_absolute": "/home/sencha/optimism-dai-bridge/contracts/l2/dai.sol", "filename_short": "contracts/l2/dai.sol", "is_dependency": false, "lines": [23, 24, 25, 26, 27, 28, 29, 30, 31, 32, 33, 34, 35, 36, 37, 38, 39, 40, 41, 42, 43, 44, 45, 46, 47, 48, 49, 50, 51, 52, 53, 54, 55, 56, 57, 58, 59, 60, 61, 62, 63, 64, 65, 66, 67, 68, 69, 70, 71, 72, 73, 74, 75, 76, 77, 78, 79, 80, 81, 82, 83, 84, 85, 86, 87, 88, 89, 90, 91, 92, 93, 94, 95, 96, 97, 98, 99, 100, 101, 102, 103, 104, 105, 106, 107, 108, 109, 110, 111, 112, 113, 114, 115, 116, 117, 118, 119, 120, 121, 122, 123, 124, 125, 126, 127, 128, 129, 130, 131, 132, 133, 134, 135, 136, 137, 138, 139, 140, 141, 142, 143, 144, 145, 146, 147, 148, 149, 150, 151, 152, 153, 154, 155, 156, 157, 158, 159, 160, 161, 162, 163, 164, 165, 166, 167, 168, 169, 170, 171, 172, 173, 174, 175, 176, 177, 178, 179, 180, 181, 182, 183, 184, 185, 186, 187, 188, 189, 190, 191, 192, 193, 194, 195, 196, 197, 198, 199, 200, 201, 202, 203, 204, 205, 206, 207, 208, 209], "starting_column": 1, "ending_column": 2}}, "signature": "permit(address,address,uint256,uint256,uint8,bytes32,bytes32)"}}, {"type": "node", "name": "require(bool,string)(block.timestamp <= deadline,Dai/permit-expired)", "source_mapping": {"start": 6142, "length": 58, "filename_used": "/home/sencha/optimism-dai-bridge/contracts/l2/dai.sol", "filename_relative": "contracts/l2/dai.sol", "filename_absolute": "/home/sencha/optimism-dai-bridge/contracts/l2/dai.sol", "filename_short": "contracts/l2/dai.sol", "is_dependency": false, "lines": [185], "starting_column": 5, "ending_column": 63}, "type_specific_fields": {"parent": {"type": "function", "name": "permit", "source_mapping": {"start": 6015, "length": 794, "filename_used": "/home/sencha/optimism-dai-bridge/contracts/l2/dai.sol", "filename_relative": "contracts/l2/dai.sol", "filename_absolute": "/home/sencha/optimism-dai-bridge/contracts/l2/dai.sol", "filename_short": "contracts/l2/dai.sol", "is_dependency": false, "lines": [184, 185, 186, 187, 188, 189, 190, 191, 192, 193, 194, 195, 196, 197, 198, 199, 200, 201, 202, 203, 204, 205, 206, 207, 208], "starting_column": 3, "ending_column": 4}, "type_specific_fields": {"parent": {"type": "contract", "name": "Dai", "source_mapping": {"start": 857, "length": 5954, "filename_used": "/home/sencha/optimism-dai-bridge/contracts/l2/dai.sol", "filename_relative": "contracts/l2/dai.sol", "filename_absolute": "/home/sencha/optimism-dai-bridge/contracts/l2/dai.sol", "filename_short": "contracts/l2/dai.sol", "is_dependency": false, "lines": [23, 24, 25, 26, 27, 28, 29, 30, 31, 32, 33, 34, 35, 36, 37, 38, 39, 40, 41, 42, 43, 44, 45, 46, 47, 48, 49, 50, 51, 52, 53, 54, 55, 56, 57, 58, 59, 60, 61, 62, 63, 64, 65, 66, 67, 68, 69, 70, 71, 72, 73, 74, 75, 76, 77, 78, 79, 80, 81, 82, 83, 84, 85, 86, 87, 88, 89, 90, 91, 92, 93, 94, 95, 96, 97, 98, 99, 100, 101, 102, 103, 104, 105, 106, 107, 108, 109, 110, 111, 112, 113, 114, 115, 116, 117, 118, 119, 120, 121, 122, 123, 124, 125, 126, 127, 128, 129, 130, 131, 132, 133, 134, 135, 136, 137, 138, 139, 140, 141, 142, 143, 144, 145, 146, 147, 148, 149, 150, 151, 152, 153, 154, 155, 156, 157, 158, 159, 160, 161, 162, 163, 164, 165, 166, 167, 168, 169, 170, 171, 172, 173, 174, 175, 176, 177, 178, 179, 180, 181, 182, 183, 184, 185, 186, 187, 188, 189, 190, 191, 192, 193, 194, 195, 196, 197, 198, 199, 200, 201, 202, 203, 204, 205, 206, 207, 208, 209], "starting_column": 1, "ending_column": 2}}, "signature": "permit(address,address,uint256,uint256,uint8,bytes32,bytes32)"}}}}], "description": "Dai.permit(address,address,uint256,uint256,uint8,bytes32,bytes32) (contracts/l2/dai.sol#184-208) uses timestamp for comparisons\n\tDangerous comparisons:\n\t- require(bool,string)(block.timestamp <= deadline,Dai/permit-expired) (contracts/l2/dai.sol#185)\n", "markdown": "[Dai.permit(address,address,uint256,uint256,uint8,bytes32,bytes32)](contracts/l2/dai.sol#L184-L208) uses timestamp for comparisons\n\tDangerous comparisons:\n\t- [require(bool,string)(block.timestamp <= deadline,Dai/permit-expired)](contracts/l2/dai.sol#L185)\n", "first_markdown_element": "contracts/l2/dai.sol#L184-L208", "id": "438f472b3716c408ab5ed26df66d13521e5b83da649f6477aa61adfc12df8b6b", "check": "timestamp", "impact": "Low", "confidence": "Medium"}, {"elements": [{"type": "variable", "name": "daiBytecode", "source_mapping": {"start": 1020, "length": 16895, "filename_used": "/home/sencha/optimism-dai-bridge/contracts/test/EscrowEchidnaTest.sol", "filename_relative": "contracts/test/EscrowEchidnaTest.sol", "filename_absolute": "/home/sencha/optimism-dai-bridge/contracts/test/EscrowEchidnaTest.sol", "filename_short": "contracts/test/EscrowEchidnaTest.sol", "is_dependency": false, "lines": [38], "starting_column": 5, "ending_column": 16900}, "type_specific_fields": {"parent": {"type": "contract", "name": "Create", "source_mapping": {"start": 998, "length": 17125, "filename_used": "/home/sencha/optimism-dai-bridge/contracts/test/EscrowEchidnaTest.sol", "filename_relative": "contracts/test/EscrowEchidnaTest.sol", "filename_absolute": "/home/sencha/optimism-dai-bridge/contracts/test/EscrowEchidnaTest.sol", "filename_short": "contracts/test/EscrowEchidnaTest.sol", "is_dependency": false, "lines": [37, 38, 39, 40, 41, 42, 43, 44, 45, 46], "starting_column": 1, "ending_column": 2}}}}], "description": "Create.daiBytecode (contracts/test/EscrowEchidnaTest.sol#38) should be constant\n", "markdown": "[Create.daiBytecode](contracts/test/EscrowEchidnaTest.sol#L38) should be constant\n", "first_markdown_element": "contracts/test/EscrowEchidnaTest.sol#L38", "id": "76cc9fe6a36e93608b3f345c7a2e6339a556c6980af4210511b6c23df02f228b", "check": "constable-states", "impact": "Optimization", "confidence": "High"}, {"elements": [{"type": "function", "name": "xDomainMessageSender", "source_mapping": {"start": 634, "length": 133, "filename_used": "/home/sencha/optimism-dai-bridge/contracts/test/EscrowEchidnaTest.sol", "filename_relative": "contracts/test/EscrowEchidnaTest.sol", "filename_absolute": "/home/sencha/optimism-dai-bridge/contracts/test/EscrowEchidnaTest.sol", "filename_short": "contracts/test/EscrowEchidnaTest.sol", "is_dependency": false, "lines": [19, 20, 21, 22, 23, 24, 25, 26], "starting_column": 3, "ending_column": 4}, "type_specific_fields": {"parent": {"type": "contract", "name": "MockMessenger", "source_mapping": {"start": 574, "length": 366, "filename_used": "/home/sencha/optimism-dai-bridge/contracts/test/EscrowEchidnaTest.sol", "filename_relative": "contracts/test/EscrowEchidnaTest.sol", "filename_absolute": "/home/sencha/optimism-dai-bridge/contracts/test/EscrowEchidnaTest.sol", "filename_short": "contracts/test/EscrowEchidnaTest.sol", "is_dependency": false, "lines": [18, 19, 20, 21, 22, 23, 24, 25, 26, 27, 28, 29, 30, 31, 32, 33, 34], "starting_column": 1, "ending_column": 2}}, "signature": "xDomainMessageSender()"}}], "description": "xDomainMessageSender() should be declared external:\n\t- MockMessenger.xDomainMessageSender() (contracts/test/EscrowEchidnaTest.sol#19-26)\n", "markdown": "xDomainMessageSender() should be declared external:\n\t- [MockMessenger.xDomainMessageSender()](contracts/test/EscrowEchidnaTest.sol#L19-L26)\n", "first_markdown_element": "contracts/test/EscrowEchidnaTest.sol#L19-L26", "id": "4daa2ca3d6da6786f7ea5e8ecdfdc16ca8601f2c12a70a5b9a1055329e7d8472", "check": "external-function", "impact": "Optimization", "confidence": "High"}]